[
  {
    "__EMPTY": "2019-11-30T15:59:17.000Z",
    "日期": "2019/12/31 23:10:16",
    "时间": "23:11:23",
    "收入": 488,
    "余额": 727.43,
    "显示摘要": "财付通-微信转账",
    "银行交易类型": "网联退款",
    "分类标识": "退款",
    "点进后图标台头": "财付通-微信转账",
    "type": "收入",
    "balance": 727.43,
    "icon": "退款",
    "amount": 488,
    "date": "2019/12/31 23:10:16",
    "ymd": "2019/12/31",
    "time": "23:11:23",
    "abstract": "财付通-微信转账",
    "title": "财付通-微信转账",
    "dealType": "网联退款"
  },
  {
    "__EMPTY": "全",
    "日期": "2019/12/31 21:43:17",
    "时间": "21:44:09",
    "支出": 268,
    "余额": 239.43,
    "显示摘要": "云视听极光-SNM",
    "银行交易类型": "网联协议支付",
    "分类标识": "休闲娱乐",
    "交易渠道": "财付通",
    "点进后图标台头": "云视听极光-SNM",
    "type": "支出",
    "balance": 239.43,
    "icon": "休闲娱乐",
    "amount": -268,
    "date": "2019/12/31 21:43:17",
    "ymd": "2019/12/31",
    "time": "21:44:09",
    "abstract": "云视听极光-SNM",
    "title": "云视听极光-SNM",
    "channel": "财付通",
    "dealType": "网联协议支付"
  },
  {
    "日期": "2019/12/31 21:42:16",
    "时间": "21:43:50",
    "收入": 300,
    "余额": 507.43,
    "显示摘要": "葛晓君8562转账",
    "银行交易类型": "行内转入",
    "分类标识": "转账给自己",
    "__EMPTY_1": "不计入",
    "点进后图标台头": "葛晓君",
    "type": "收入",
    "balance": 507.43,
    "icon": "转账给自己",
    "amount": 300,
    "date": "2019/12/31 21:42:16",
    "ymd": "2019/12/31",
    "time": "21:43:50",
    "abstract": "葛晓君8562转账",
    "title": "葛晓君",
    "dealType": "行内转入"
  },
  {
    "日期": "2019/12/30 23:10:16",
    "时间": "23:11:10",
    "支出": 488,
    "余额": 207.43,
    "显示摘要": "财付通-微信转账",
    "银行交易类型": "网联协议支付",
    "分类标识": "转账给他人",
    "交易渠道": "财付通",
    "点进后图标台头": "微信转账",
    "type": "支出",
    "balance": 207.43,
    "icon": "转账给他人",
    "amount": -488,
    "date": "2019/12/30 23:10:16",
    "ymd": "2019/12/30",
    "time": "23:11:10",
    "abstract": "财付通-微信转账",
    "title": "微信转账",
    "channel": "财付通",
    "channel1": "财付通",
    "channel2": "财付通",
    "channel3": "财付通",
    "dealType": "网联协议支付"
  },
  {
    "日期": "2019/12/30 23:07:17",
    "时间": "23:08:08",
    "收入": 500,
    "余额": 695.43,
    "显示摘要": "葛晓君8562转账",
    "银行交易类型": "行内转入",
    "分类标识": "转账给自己",
    "__EMPTY_1": "不计入",
    "点进后图标台头": "葛晓君",
    "type": "收入",
    "balance": 695.43,
    "icon": "转账给自己",
    "amount": 500,
    "date": "2019/12/30 23:07:17",
    "ymd": "2019/12/30",
    "time": "23:08:08",
    "abstract": "葛晓君8562转账",
    "title": "葛晓君",
    "dealType": "行内转入"
  },
  {
    "日期": "2019/12/30 13:34:16",
    "时间": "13:35:03",
    "支出": 100,
    "余额": 195.43,
    "显示摘要": "财付通-国网北京电力",
    "银行交易类型": "网联协议支付",
    "分类标识": "充值缴费",
    "交易渠道": "财付通",
    "点进后图标台头": "国网北京电力",
    "type": "支出",
    "balance": 195.43,
    "icon": "充值缴费",
    "amount": -100,
    "date": "2019/12/30 13:34:16",
    "ymd": "2019/12/30",
    "time": "13:35:03",
    "abstract": "财付通-国网北京电力",
    "title": "国网北京电力",
    "channel": "财付通",
    "dealType": "网联协议支付"
  },
  {
    "日期": "2019/12/29 11:08:16",
    "时间": "11:09:07",
    "支出": 50,
    "余额": 295.43,
    "显示摘要": "支付宝-上海捷羿软件系统...",
    "银行交易类型": "网联协议支付",
    "分类标识": "出行",
    "交易渠道": "支付宝",
    "点进后图标台头": "上海捷羿软件系统有限公司",
    "type": "支出",
    "balance": 295.43,
    "icon": "出行",
    "amount": -50,
    "date": "2019/12/29 11:08:16",
    "ymd": "2019/12/29",
    "time": "11:09:07",
    "abstract": "支付宝-上海捷羿软件系统...",
    "title": "上海捷羿软件系统有限公司",
    "channel": "支付宝",
    "dealType": "网联协议支付"
  },
  {
    "日期": "2019/12/25 21:49:16",
    "时间": "21:50:53",
    "支出": 232.74,
    "余额": 345.43,
    "显示摘要": "财付通-微信转账",
    "银行交易类型": "网联协议支付",
    "分类标识": "转账给他人",
    "交易渠道": "财付通",
    "点进后图标台头": "微信转账",
    "type": "支出",
    "balance": 345.43,
    "icon": "转账给他人",
    "amount": -232.74,
    "date": "2019/12/25 21:49:16",
    "ymd": "2019/12/25",
    "time": "21:50:53",
    "abstract": "财付通-微信转账",
    "title": "微信转账",
    "channel": "财付通",
    "dealType": "网联协议支付"
  },
  {
    "日期": "2019/12/25 21:49:16",
    "时间": "21:50:45",
    "收入": 500,
    "余额": 578.17,
    "显示摘要": "葛晓君8562转账",
    "银行交易类型": "行内转入",
    "分类标识": "转账给自己",
    "__EMPTY_1": "不计入",
    "点进后图标台头": "葛晓君",
    "type": "收入",
    "balance": 578.17,
    "icon": "转账给自己",
    "amount": 500,
    "date": "2019/12/25 21:49:16",
    "ymd": "2019/12/25",
    "time": "21:50:45",
    "abstract": "葛晓君8562转账",
    "title": "葛晓君",
    "dealType": "行内转入"
  },
  {
    "日期": "2019/12/24 21:23:17",
    "时间": "21:24:44",
    "支出": 4000,
    "余额": 78.17,
    "显示摘要": "财付通-微信转账",
    "银行交易类型": "网联协议支付",
    "分类标识": "转账给他人",
    "交易渠道": "财付通",
    "点进后图标台头": "微信转账",
    "type": "支出",
    "balance": 78.17,
    "icon": "转账给他人",
    "amount": -4000,
    "date": "2019/12/24 21:23:17",
    "ymd": "2019/12/24",
    "time": "21:24:44",
    "abstract": "财付通-微信转账",
    "title": "微信转账",
    "channel": "财付通",
    "dealType": "网联协议支付"
  },
  {
    "日期": "2019/12/24 21:22:16",
    "时间": "21:23:31",
    "收入": 4000,
    "余额": 4078.17,
    "显示摘要": "葛晓君8562转账",
    "银行交易类型": "行内转入",
    "分类标识": "转账给自己",
    "__EMPTY_1": "不计入",
    "点进后图标台头": "葛晓君",
    "type": "收入",
    "balance": 4078.17,
    "icon": "转账给自己",
    "amount": 4000,
    "date": "2019/12/24 21:22:16",
    "ymd": "2019/12/24",
    "time": "21:23:31",
    "abstract": "葛晓君8562转账",
    "title": "葛晓君",
    "dealType": "行内转入"
  },
  {
    "日期": "2019/12/21 12:39:17",
    "时间": "12:40:09",
    "收入": 0.19,
    "余额": 78.17,
    "显示摘要": "结息：0.19扣税：0.00",
    "银行交易类型": "账户结息",
    "分类标识": "投资收益",
    "点进后图标台头": "结息：0.19扣税：0.00",
    "type": "收入",
    "balance": 78.17,
    "icon": "投资收益",
    "amount": 0.19,
    "date": "2019/12/21 12:39:17",
    "ymd": "2019/12/21",
    "time": "12:40:09",
    "abstract": "结息：0.19扣税：0.00",
    "title": "结息：0.19扣税：0.00",
    "dealType": "账户结息"
  },
  {
    "日期": "2019/12/11 23:15:16",
    "时间": "23:16:23",
    "支出": 6022.02,
    "余额": 77.98,
    "显示摘要": "支付宝-花呗",
    "银行交易类型": "网联协议支付",
    "分类标识": "还款",
    "交易渠道": "支付宝",
    "点进后图标台头": "花呗",
    "type": "支出",
    "balance": 77.98,
    "icon": "还款",
    "amount": -6022.02,
    "date": "2019/12/11 23:15:16",
    "ymd": "2019/12/11",
    "time": "23:16:23",
    "abstract": "支付宝-花呗",
    "title": "花呗",
    "channel": "支付宝",
    "dealType": "网联协议支付"
  },
  {
    "日期": "2019/12/11 23:14:17",
    "时间": "23:15:12",
    "收入": 6100,
    "余额": 6100,
    "显示摘要": "葛晓君8562转账",
    "银行交易类型": "行内转入",
    "分类标识": "转账给自己",
    "__EMPTY_1": "不计入",
    "点进后图标台头": "葛晓君",
    "type": "收入",
    "balance": 6100,
    "icon": "转账给自己",
    "amount": 6100,
    "date": "2019/12/11 23:14:17",
    "ymd": "2019/12/11",
    "time": "23:15:12",
    "abstract": "葛晓君8562转账",
    "title": "葛晓君",
    "dealType": "行内转入"
  },
  {
    "日期": "2019/12/08 18:05:17",
    "时间": "18:06:09",
    "支出": 450.41,
    "余额": 0,
    "显示摘要": "20191208A0011001...",
    "银行交易类型": "信用卡存款",
    "分类标识": "还招行信用卡",
    "__EMPTY_1": "不计入",
    "点进后图标台头": "20191208A00110013499",
    "type": "支出",
    "balance": 0,
    "icon": "还招行信用卡",
    "amount": -450.41,
    "date": "2019/12/08 18:05:17",
    "ymd": "2019/12/08",
    "time": "18:06:09",
    "abstract": "20191208A0011001...",
    "title": "20191208A00110013499",
    "dealType": "信用卡存款"
  },
  {
    "income": 488.19,
    "expend": 11160.76,
    "hz": "201912"
  },
  {
    "__EMPTY": "2019-10-31T15:59:17.000Z",
    "日期": "2019/11/24 11:38:17",
    "时间": "11:39:03",
    "支出": 29,
    "余额": 450.41,
    "显示摘要": "财付通-京东商城平台商户",
    "银行交易类型": "网联协议支付",
    "分类标识": "购物",
    "交易渠道": "财付通",
    "点进后图标台头": "京东商城平台商户",
    "type": "支出",
    "balance": 450.41,
    "icon": "购物",
    "amount": -29,
    "date": "2019/11/24 11:38:17",
    "ymd": "2019/11/24",
    "time": "11:39:03",
    "abstract": "财付通-京东商城平台商户",
    "title": "京东商城平台商户",
    "channel": "财付通",
    "dealType": "网联协议支付"
  },
  {
    "日期": "2019/11/23 09:38:16",
    "时间": "09:39:32",
    "支出": 584,
    "余额": 479.41,
    "显示摘要": "财付通-微信转账",
    "银行交易类型": "网联协议支付",
    "分类标识": "转账给他人",
    "交易渠道": "财付通",
    "点进后图标台头": "微信转账",
    "type": "支出",
    "balance": 479.41,
    "icon": "转账给他人",
    "amount": -584,
    "date": "2019/11/23 09:38:16",
    "ymd": "2019/11/23",
    "time": "09:39:32",
    "abstract": "财付通-微信转账",
    "title": "微信转账",
    "channel": "财付通",
    "dealType": "网联协议支付"
  },
  {
    "日期": "2019/11/23 09:37:17",
    "时间": "09:38:12",
    "收入": 584,
    "余额": 1063.41,
    "显示摘要": "葛晓君8562转账",
    "银行交易类型": "行内转入",
    "分类标识": "转账给自己",
    "__EMPTY_1": "不计入",
    "点进后图标台头": "葛晓君",
    "type": "收入",
    "balance": 1063.41,
    "icon": "转账给自己",
    "amount": 584,
    "date": "2019/11/23 09:37:17",
    "ymd": "2019/11/23",
    "time": "09:38:12",
    "abstract": "葛晓君8562转账",
    "title": "葛晓君",
    "dealType": "行内转入"
  },
  {
    "日期": "2019/11/22 19:48:16",
    "时间": "19:49:12",
    "支出": 100,
    "余额": 479.41,
    "显示摘要": "财付通-微信转账",
    "银行交易类型": "网联协议支付",
    "分类标识": "转账给他人",
    "交易渠道": "财付通",
    "点进后图标台头": "微信转账",
    "type": "支出",
    "balance": 479.41,
    "icon": "转账给他人",
    "amount": -100,
    "date": "2019/11/22 19:48:16",
    "ymd": "2019/11/22",
    "time": "19:49:12",
    "abstract": "财付通-微信转账",
    "title": "微信转账",
    "channel": "财付通",
    "dealType": "网联协议支付"
  },
  {
    "日期": "2019/11/21 10:08:17",
    "时间": "10:09:08",
    "支出": 29,
    "余额": 579.41,
    "显示摘要": "财付通-国广东方",
    "银行交易类型": "网联协议支付",
    "分类标识": "充值缴费",
    "交易渠道": "财付通",
    "点进后图标台头": "国广东方",
    "type": "支出",
    "balance": 579.41,
    "icon": "充值缴费",
    "amount": -29,
    "date": "2019/11/21 10:08:17",
    "ymd": "2019/11/21",
    "time": "10:09:08",
    "abstract": "财付通-国广东方",
    "title": "国广东方",
    "channel": "财付通",
    "dealType": "网联协议支付"
  },
  {
    "日期": "2019/11/19 08:20:17",
    "时间": "08:21:08",
    "支出": 23.9,
    "余额": 608.41,
    "显示摘要": "财付通-京东商城平台商户",
    "银行交易类型": "银联快捷支付",
    "分类标识": "购物",
    "交易渠道": "财付通",
    "点进后图标台头": "京东商城平台商户",
    "type": "支出",
    "balance": 608.41,
    "icon": "购物",
    "amount": -23.9,
    "date": "2019/11/19 08:20:17",
    "ymd": "2019/11/19",
    "time": "08:21:08",
    "abstract": "财付通-京东商城平台商户",
    "title": "京东商城平台商户",
    "channel": "财付通",
    "dealType": "银联快捷支付"
  },
  {
    "日期": "2019/11/17 23:00:17",
    "时间": "23:01:09",
    "收入": 8,
    "余额": 632.31,
    "显示摘要": "财付通-微信转账",
    "银行交易类型": "网联退款",
    "分类标识": "退款",
    "点进后图标台头": "财付通-微信转账",
    "type": "收入",
    "balance": 632.31,
    "icon": "退款",
    "amount": 8,
    "date": "2019/11/17 23:00:17",
    "ymd": "2019/11/17",
    "time": "23:01:09",
    "abstract": "财付通-微信转账",
    "title": "财付通-微信转账",
    "dealType": "网联退款"
  },
  {
    "日期": "2019/11/17 22:49:17",
    "时间": "22:50:14",
    "支出": 8,
    "余额": 624.31,
    "显示摘要": "财付通-微信转账",
    "银行交易类型": "网联协议支付",
    "分类标识": "转账给他人",
    "交易渠道": "财付通",
    "点进后图标台头": "微信转账",
    "type": "支出",
    "balance": 624.31,
    "icon": "转账给他人",
    "amount": -8,
    "date": "2019/11/17 22:49:17",
    "ymd": "2019/11/17",
    "time": "22:50:14",
    "abstract": "财付通-微信转账",
    "title": "微信转账",
    "channel": "财付通",
    "dealType": "网联协议支付"
  },
  {
    "日期": "2019/11/17 22:44:17",
    "时间": "22:45:34",
    "支出": 280,
    "余额": 632.31,
    "显示摘要": "财付通-腾讯财付通-北",
    "银行交易类型": "银联快捷支付",
    "分类标识": "转账给他人",
    "交易渠道": "财付通",
    "点进后图标台头": "微信转账",
    "type": "支出",
    "balance": 632.31,
    "icon": "转账给他人",
    "amount": -280,
    "date": "2019/11/17 22:44:17",
    "ymd": "2019/11/17",
    "time": "22:45:34",
    "abstract": "财付通-腾讯财付通-北",
    "title": "微信转账",
    "channel": "财付通",
    "dealType": "银联快捷支付"
  },
  {
    "日期": "2019/11/17 22:05:16",
    "时间": "22:06:21",
    "支出": 11088,
    "余额": 912.31,
    "显示摘要": "财付通-微信支付-微...",
    "银行交易类型": "银联快捷支付",
    "分类标识": "转账给他人",
    "交易渠道": "财付通",
    "点进后图标台头": "微信转账",
    "type": "支出",
    "balance": 912.31,
    "icon": "转账给他人",
    "amount": -11088,
    "date": "2019/11/17 22:05:16",
    "ymd": "2019/11/17",
    "time": "22:06:21",
    "abstract": "财付通-微信支付-微...",
    "title": "微信转账",
    "channel": "财付通",
    "dealType": "银联快捷支付"
  },
  {
    "日期": "2019/11/17 22:04:17",
    "时间": "22:05:01",
    "收入": 12000,
    "余额": 12000.31,
    "显示摘要": "葛晓君8562转账",
    "银行交易类型": "行内转入",
    "分类标识": "转账给自己",
    "__EMPTY_1": "不计入",
    "点进后图标台头": "葛晓君",
    "type": "收入",
    "balance": 12000.31,
    "icon": "转账给自己",
    "amount": 12000,
    "date": "2019/11/17 22:04:17",
    "ymd": "2019/11/17",
    "time": "22:05:01",
    "abstract": "葛晓君8562转账",
    "title": "葛晓君",
    "dealType": "行内转入"
  },
  {
    "日期": "2019/11/17 18:20:16",
    "时间": "18:21:08",
    "支出": 69.4,
    "余额": 0.31,
    "显示摘要": "财付通-腾讯财付通-北",
    "银行交易类型": "银联快捷支付",
    "分类标识": "购物",
    "交易渠道": "财付通",
    "点进后图标台头": "北京SKP",
    "type": "支出",
    "balance": 0.31,
    "icon": "购物",
    "amount": -69.4,
    "date": "2019/11/17 18:20:16",
    "ymd": "2019/11/17",
    "time": "18:21:08",
    "abstract": "财付通-腾讯财付通-北",
    "title": "北京SKP",
    "channel": "财付通",
    "dealType": "银联快捷支付"
  },
  {
    "日期": "2019/11/17 17:33:16",
    "时间": "17:34:34",
    "支出": 19,
    "余额": 69.71,
    "显示摘要": "财付通-腾讯财付通-北",
    "银行交易类型": "银联快捷支付",
    "分类标识": "购物",
    "交易渠道": "财付通",
    "点进后图标台头": "北京SKP",
    "type": "支出",
    "balance": 69.71,
    "icon": "购物",
    "amount": -19,
    "date": "2019/11/17 17:33:16",
    "ymd": "2019/11/17",
    "time": "17:34:34",
    "abstract": "财付通-腾讯财付通-北",
    "title": "北京SKP",
    "channel": "财付通",
    "dealType": "银联快捷支付"
  },
  {
    "日期": "2019/11/17 10:26:17",
    "时间": "10:27:23",
    "支出": 238.29,
    "余额": 88.71,
    "显示摘要": "财付通-每日优鲜电...",
    "银行交易类型": "网联协议支付",
    "分类标识": "餐饮",
    "交易渠道": "财付通",
    "点进后图标台头": "北京每日优鲜电子商务",
    "type": "支出",
    "balance": 88.71,
    "icon": "餐饮",
    "amount": -238.29,
    "date": "2019/11/17 10:26:17",
    "ymd": "2019/11/17",
    "time": "10:27:23",
    "abstract": "财付通-每日优鲜电...",
    "title": "北京每日优鲜电子商务",
    "channel": "财付通",
    "dealType": "网联协议支付"
  },
  {
    "日期": "2019/11/17 10:25:16",
    "时间": "10:26:55",
    "收入": 300,
    "余额": 327,
    "显示摘要": "葛晓君8562转账",
    "银行交易类型": "行内转入",
    "分类标识": "转账给自己",
    "__EMPTY_1": "不计入",
    "点进后图标台头": "葛晓君",
    "type": "收入",
    "balance": 327,
    "icon": "转账给自己",
    "amount": 300,
    "date": "2019/11/17 10:25:16",
    "ymd": "2019/11/17",
    "time": "10:26:55",
    "abstract": "葛晓君8562转账",
    "title": "葛晓君",
    "dealType": "行内转入"
  },
  {
    "日期": "2019/11/13 08:29:17",
    "时间": "08:30:13",
    "支出": 42,
    "余额": 27,
    "显示摘要": "财付通-滴滴出行",
    "银行交易类型": "网联协议支付",
    "分类标识": "出行",
    "交易渠道": "财付通",
    "点进后图标台头": "滴滴出行",
    "type": "支出",
    "balance": 27,
    "icon": "出行",
    "amount": -42,
    "date": "2019/11/13 08:29:17",
    "ymd": "2019/11/13",
    "time": "08:30:13",
    "abstract": "财付通-滴滴出行",
    "title": "滴滴出行",
    "channel": "财付通",
    "dealType": "网联协议支付"
  },
  {
    "日期": "2019/11/13 08:27:17",
    "时间": "08:28:12",
    "支出": 1000,
    "余额": 69,
    "显示摘要": "财付通-首汽约车",
    "银行交易类型": "网联协议支付",
    "分类标识": "出行",
    "交易渠道": "财付通",
    "点进后图标台头": "首汽约车",
    "type": "支出",
    "balance": 69,
    "icon": "出行",
    "amount": -1000,
    "date": "2019/11/13 08:27:17",
    "ymd": "2019/11/13",
    "time": "08:28:12",
    "abstract": "财付通-首汽约车",
    "title": "首汽约车",
    "channel": "财付通",
    "dealType": "网联协议支付"
  },
  {
    "日期": "2019/11/13 08:26:16",
    "时间": "08:27:01",
    "收入": 1000,
    "余额": 1069,
    "显示摘要": "葛晓君8562转账",
    "银行交易类型": "行内转入",
    "分类标识": "转账给自己",
    "__EMPTY_1": "不计入",
    "点进后图标台头": "葛晓君",
    "type": "收入",
    "balance": 1069,
    "icon": "转账给自己",
    "amount": 1000,
    "date": "2019/11/13 08:26:16",
    "ymd": "2019/11/13",
    "time": "08:27:01",
    "abstract": "葛晓君8562转账",
    "title": "葛晓君",
    "dealType": "行内转入"
  },
  {
    "日期": "2019/11/12 16:43:16",
    "时间": "16:44:23",
    "支出": 16,
    "余额": 69,
    "显示摘要": "财付通-微信支付-百盛",
    "银行交易类型": "银联快捷支付",
    "分类标识": "购物",
    "交易渠道": "财付通",
    "点进后图标台头": "百盛商业发展有限公司",
    "type": "支出",
    "balance": 69,
    "icon": "购物",
    "amount": -16,
    "date": "2019/11/12 16:43:16",
    "ymd": "2019/11/12",
    "time": "16:44:23",
    "abstract": "财付通-微信支付-百盛",
    "title": "百盛商业发展有限公司",
    "channel": "财付通",
    "dealType": "银联快捷支付"
  },
  {
    "日期": "2019/11/11 18:44:17",
    "时间": "18:45:12",
    "支出": 2440,
    "余额": 85,
    "显示摘要": "财付通-微信支付-苗家...",
    "银行交易类型": "银联快捷支付",
    "分类标识": "其他支出",
    "交易渠道": "财付通",
    "点进后图标台头": "苗家圆圆",
    "type": "支出",
    "balance": 85,
    "icon": "其他支出",
    "amount": -2440,
    "date": "2019/11/11 18:44:17",
    "ymd": "2019/11/11",
    "time": "18:45:12",
    "abstract": "财付通-微信支付-苗家...",
    "title": "苗家圆圆",
    "channel": "财付通",
    "dealType": "银联快捷支付"
  },
  {
    "日期": "2019/11/11 18:43:17",
    "时间": "18:44:02",
    "收入": 2440,
    "余额": 2525,
    "显示摘要": "葛晓君8562转账",
    "银行交易类型": "行内转入",
    "分类标识": "转账给自己",
    "__EMPTY_1": "不计入",
    "点进后图标台头": "葛晓君",
    "type": "收入",
    "balance": 2525,
    "icon": "转账给自己",
    "amount": 2440,
    "date": "2019/11/11 18:43:17",
    "ymd": "2019/11/11",
    "time": "18:44:02",
    "abstract": "葛晓君8562转账",
    "title": "葛晓君",
    "dealType": "行内转入"
  },
  {
    "日期": "2019/11/11 14:56:17",
    "时间": "14:57:01",
    "支出": 2655,
    "余额": 85,
    "显示摘要": "财付通-微信支付-微...",
    "银行交易类型": "银联快捷支付",
    "分类标识": "转账给他人",
    "交易渠道": "财付通",
    "点进后图标台头": "微信转账",
    "type": "支出",
    "balance": 85,
    "icon": "转账给他人",
    "amount": -2655,
    "date": "2019/11/11 14:56:17",
    "ymd": "2019/11/11",
    "time": "14:57:01",
    "abstract": "财付通-微信支付-微...",
    "title": "微信转账",
    "channel": "财付通",
    "dealType": "银联快捷支付"
  },
  {
    "日期": "2019/11/11 14:55:24",
    "时间": "14:56:45",
    "收入": 2655,
    "余额": 2740,
    "显示摘要": "葛晓君8562转账",
    "银行交易类型": "行内转入",
    "分类标识": "转账给自己",
    "__EMPTY_1": "不计入",
    "点进后图标台头": "葛晓君",
    "type": "收入",
    "balance": 2740,
    "icon": "转账给自己",
    "amount": 2655,
    "date": "2019/11/11 14:55:24",
    "ymd": "2019/11/11",
    "time": "14:56:45",
    "abstract": "葛晓君8562转账",
    "title": "葛晓君",
    "dealType": "行内转入"
  },
  {
    "日期": "2019/11/11 14:39:16",
    "时间": "14:40:24",
    "支出": 26,
    "余额": 85,
    "显示摘要": "财付通-闪送",
    "银行交易类型": "网联协议支付",
    "分类标识": "其他支出",
    "交易渠道": "财付通",
    "点进后图标台头": "闪送",
    "type": "支出",
    "balance": 85,
    "icon": "其他支出",
    "amount": -26,
    "date": "2019/11/11 14:39:16",
    "ymd": "2019/11/11",
    "time": "14:40:24",
    "abstract": "财付通-闪送",
    "title": "闪送",
    "channel": "财付通",
    "dealType": "网联协议支付"
  },
  {
    "日期": "2019/11/11 14:35:16",
    "时间": "14:36:03",
    "收入": 26,
    "余额": 111,
    "显示摘要": "退 财付通-闪送",
    "银行交易类型": "网联退款",
    "分类标识": "退款",
    "点进后图标台头": "财付通-闪送",
    "type": "收入",
    "balance": 111,
    "icon": "退款",
    "amount": 26,
    "date": "2019/11/11 14:35:16",
    "ymd": "2019/11/11",
    "time": "14:36:03",
    "abstract": "退 财付通-闪送",
    "title": "财付通-闪送",
    "dealType": "网联退款"
  },
  {
    "日期": "2019/11/11 14:32:16",
    "时间": "14:33:22",
    "支出": 26,
    "余额": 85,
    "显示摘要": "财付通-闪送",
    "银行交易类型": "网联协议支付",
    "分类标识": "其他支出",
    "交易渠道": "财付通",
    "点进后图标台头": "闪送",
    "type": "支出",
    "balance": 85,
    "icon": "其他支出",
    "amount": -26,
    "date": "2019/11/11 14:32:16",
    "ymd": "2019/11/11",
    "time": "14:33:22",
    "abstract": "财付通-闪送",
    "title": "闪送",
    "channel": "财付通",
    "dealType": "网联协议支付"
  },
  {
    "日期": "2019/11/11 14:32:16",
    "时间": "14:33:08",
    "收入": 100,
    "余额": 111,
    "显示摘要": "葛晓君8562转账",
    "银行交易类型": "行内转入",
    "分类标识": "转账给自己",
    "__EMPTY_1": "不计入",
    "点进后图标台头": "葛晓君",
    "type": "收入",
    "balance": 111,
    "icon": "转账给自己",
    "amount": 100,
    "date": "2019/11/11 14:32:16",
    "ymd": "2019/11/11",
    "time": "14:33:08",
    "abstract": "葛晓君8562转账",
    "title": "葛晓君",
    "dealType": "行内转入"
  },
  {
    "日期": "2019/11/10 23:35:16",
    "时间": "23:36:05",
    "支出": 2093,
    "余额": 11,
    "显示摘要": "支付宝-特约商户",
    "银行交易类型": "网联协议支付",
    "分类标识": "其他支出",
    "交易渠道": "支付宝",
    "点进后图标台头": "特约商户",
    "type": "支出",
    "balance": 11,
    "icon": "其他支出",
    "amount": -2093,
    "date": "2019/11/10 23:35:16",
    "ymd": "2019/11/10",
    "time": "23:36:05",
    "abstract": "支付宝-特约商户",
    "title": "特约商户",
    "channel": "支付宝",
    "dealType": "网联协议支付"
  },
  {
    "日期": "2019/11/10 23:34:17",
    "时间": "23:35:34",
    "收入": 2000,
    "余额": 2104,
    "显示摘要": "葛晓君8562转账",
    "银行交易类型": "行内转入",
    "分类标识": "转账给自己",
    "__EMPTY_1": "不计入",
    "点进后图标台头": "葛晓君",
    "type": "收入",
    "balance": 2104,
    "icon": "转账给自己",
    "amount": 2000,
    "date": "2019/11/10 23:34:17",
    "ymd": "2019/11/10",
    "time": "23:35:34",
    "abstract": "葛晓君8562转账",
    "title": "葛晓君",
    "dealType": "行内转入"
  },
  {
    "日期": "2019/11/09 21:35:17",
    "时间": "21:36:57",
    "支出": 1000,
    "余额": 104,
    "显示摘要": "财付通-微信转账",
    "银行交易类型": "网联协议支付",
    "分类标识": "转账给他人",
    "交易渠道": "财付通",
    "点进后图标台头": "微信转账",
    "type": "支出",
    "balance": 104,
    "icon": "转账给他人",
    "amount": -1000,
    "date": "2019/11/09 21:35:17",
    "ymd": "2019/11/09",
    "time": "21:36:57",
    "abstract": "财付通-微信转账",
    "title": "微信转账",
    "channel": "财付通",
    "dealType": "网联协议支付"
  },
  {
    "日期": "2019/11/09 17:15:16",
    "时间": "17:16:56",
    "支出": 2725,
    "余额": 1104,
    "显示摘要": "银联消费异构-三里屯店",
    "银行交易类型": "银联POS消费",
    "分类标识": "其他支出",
    "交易渠道": "无",
    "点进后图标台头": "异构-三里屯店",
    "type": "支出",
    "balance": 1104,
    "icon": "其他支出",
    "amount": -2725,
    "date": "2019/11/09 17:15:16",
    "ymd": "2019/11/09",
    "time": "17:16:56",
    "abstract": "银联消费异构-三里屯店",
    "title": "异构-三里屯店",
    "channel": "无",
    "dealType": "银联POS消费"
  },
  {
    "__EMPTY": "重点条目",
    "日期": "2019/11/03 21:25:17",
    "时间": "21:26:35",
    "支出": 8951,
    "余额": 3829,
    "显示摘要": "张强9096转账",
    "银行交易类型": "转账汇款",
    "分类标识": "转账给他人",
    "点进后图标台头": "张强",
    "__EMPTY_2": "招商银行上海分行营业部",
    "__EMPTY_3": "4682********9096",
    "type": "支出",
    "balance": 3829,
    "icon": "转账给他人",
    "amount": -8951,
    "date": "2019/11/03 21:25:17",
    "ymd": "2019/11/03",
    "time": "21:26:35",
    "abstract": "张强9096转账",
    "title": "张强",
    "dealType": "转账汇款"
  },
  {
    "日期": "2019/11/03 21:14:17",
    "时间": "21:15:26",
    "支出": 99.6,
    "余额": 12780,
    "显示摘要": "财付通-手机充值",
    "银行交易类型": "网联协议支付",
    "分类标识": "充值缴费",
    "交易渠道": "财付通",
    "点进后图标台头": "手机充值",
    "type": "支出",
    "balance": 12780,
    "icon": "充值缴费",
    "amount": -99.6,
    "date": "2019/11/03 21:14:17",
    "ymd": "2019/11/03",
    "time": "21:15:26",
    "abstract": "财付通-手机充值",
    "title": "手机充值",
    "channel": "财付通",
    "dealType": "网联协议支付"
  },
  {
    "日期": "2019/11/03 21:12:17",
    "时间": "21:13:23",
    "支出": 10000,
    "余额": 12879.6,
    "显示摘要": "财付通-首汽约车",
    "银行交易类型": "网联协议支付",
    "分类标识": "出行",
    "交易渠道": "财付通",
    "点进后图标台头": "首汽约车",
    "type": "支出",
    "balance": 12879.6,
    "icon": "出行",
    "amount": -10000,
    "date": "2019/11/03 21:12:17",
    "ymd": "2019/11/03",
    "time": "21:13:23",
    "abstract": "财付通-首汽约车",
    "title": "首汽约车",
    "channel": "财付通",
    "dealType": "网联协议支付"
  },
  {
    "__EMPTY": "****",
    "日期": "2019/11/03 18:44:17",
    "时间": "18:45:36",
    "支出": 216.72,
    "余额": 13879.6,
    "显示摘要": "银联消费北京家爱福美超...",
    "银行交易类型": "银联POS消费",
    "分类标识": "超市便利",
    "交易渠道": "无",
    "点进后图标台头": "北京家爱福美超市",
    "type": "支出",
    "balance": 13879.6,
    "icon": "超市便利",
    "amount": -216.72,
    "date": "2019/11/03 18:44:17",
    "ymd": "2019/11/03",
    "time": "18:45:36",
    "abstract": "银联消费北京家爱福美超...",
    "title": "北京家爱福美超市",
    "channel": "无",
    "dealType": "银联POS消费"
  },
  {
    "日期": "2019/11/03 15:25:17",
    "时间": "15:26:20",
    "支出": 50,
    "余额": 14096.32,
    "显示摘要": "支付宝-上海捷羿软件系统...",
    "银行交易类型": "网联协议支付",
    "分类标识": "出行",
    "交易渠道": "支付宝",
    "点进后图标台头": "上海捷羿软件系统有限公司",
    "type": "支出",
    "balance": 14096.32,
    "icon": "出行",
    "amount": -50,
    "date": "2019/11/03 15:25:17",
    "ymd": "2019/11/03",
    "time": "15:26:20",
    "abstract": "支付宝-上海捷羿软件系统...",
    "title": "上海捷羿软件系统有限公司",
    "channel": "支付宝",
    "dealType": "网联协议支付"
  },
  {
    "日期": "2019/11/03 12:55:17",
    "时间": "12:56:27",
    "支出": 37.9,
    "余额": 14146.32,
    "显示摘要": "财付通-京东商城平台商户",
    "银行交易类型": "网联协议支付",
    "分类标识": "购物",
    "交易渠道": "财付通",
    "点进后图标台头": "京东商城平台商户",
    "type": "支出",
    "balance": 14146.32,
    "icon": "购物",
    "amount": -37.9,
    "date": "2019/11/03 12:55:17",
    "ymd": "2019/11/03",
    "time": "12:56:27",
    "abstract": "财付通-京东商城平台商户",
    "title": "京东商城平台商户",
    "channel": "财付通",
    "dealType": "网联协议支付"
  },
  {
    "日期": "2019/11/02 18:09:16",
    "时间": "18:10:39",
    "支出": 470,
    "余额": 14184.22,
    "显示摘要": "财付通-苗家圆圆",
    "银行交易类型": "网联协议支付",
    "分类标识": "其他支出",
    "交易渠道": "财付通",
    "点进后图标台头": "苗家圆圆",
    "type": "支出",
    "balance": 14184.22,
    "icon": "其他支出",
    "amount": -470,
    "date": "2019/11/02 18:09:16",
    "ymd": "2019/11/02",
    "time": "18:10:39",
    "abstract": "财付通-苗家圆圆",
    "title": "苗家圆圆",
    "channel": "财付通",
    "dealType": "网联协议支付"
  },
  {
    "日期": "2019/11/02 18:08:16",
    "时间": "18:09:06",
    "支出": 155,
    "余额": 14654.22,
    "显示摘要": "财付通-京东商城平台商户",
    "银行交易类型": "网联协议支付",
    "分类标识": "购物",
    "交易渠道": "财付通",
    "点进后图标台头": "京东商城平台商户",
    "type": "支出",
    "balance": 14654.22,
    "icon": "购物",
    "amount": -155,
    "date": "2019/11/02 18:08:16",
    "ymd": "2019/11/02",
    "time": "18:09:06",
    "abstract": "财付通-京东商城平台商户",
    "title": "京东商城平台商户",
    "channel": "财付通",
    "dealType": "网联协议支付"
  },
  {
    "日期": "2019/11/02 18:06:16",
    "时间": "18:07:01",
    "支出": 470,
    "余额": 14809.22,
    "显示摘要": "财付通-京东商城平台商户",
    "银行交易类型": "网联协议支付",
    "分类标识": "购物",
    "交易渠道": "财付通",
    "点进后图标台头": "京东商城平台商户",
    "type": "支出",
    "balance": 14809.22,
    "icon": "购物",
    "amount": -470,
    "date": "2019/11/02 18:06:16",
    "ymd": "2019/11/02",
    "time": "18:07:01",
    "abstract": "财付通-京东商城平台商户",
    "title": "京东商城平台商户",
    "channel": "财付通",
    "dealType": "网联协议支付"
  },
  {
    "日期": "2019/11/02 18:05:17",
    "时间": "18:06:24",
    "收入": 15000,
    "余额": 15279.22,
    "显示摘要": "葛晓君8562转账",
    "银行交易类型": "行内转入",
    "分类标识": "转账给自己",
    "__EMPTY_1": "不计入",
    "点进后图标台头": "葛晓君",
    "type": "收入",
    "balance": 15279.22,
    "icon": "转账给自己",
    "amount": 15000,
    "date": "2019/11/02 18:05:17",
    "ymd": "2019/11/02",
    "time": "18:06:24",
    "abstract": "葛晓君8562转账",
    "title": "葛晓君",
    "dealType": "行内转入"
  },
  {
    "日期": "2019/11/02 18:04:16",
    "时间": "18:05:02",
    "支出": 46,
    "余额": 279.22,
    "显示摘要": "财付通-京东商城平台商户",
    "银行交易类型": "网联协议支付",
    "分类标识": "购物",
    "交易渠道": "财付通",
    "点进后图标台头": "京东商城平台商户",
    "type": "支出",
    "balance": 279.22,
    "icon": "购物",
    "amount": -46,
    "date": "2019/11/02 18:04:16",
    "ymd": "2019/11/02",
    "time": "18:05:02",
    "abstract": "财付通-京东商城平台商户",
    "title": "京东商城平台商户",
    "channel": "财付通",
    "dealType": "网联协议支付"
  },
  {
    "日期": "2019/11/02 12:42:16",
    "时间": "12:43:34",
    "支出": 36,
    "余额": 325.22,
    "显示摘要": "财付通-腾讯财付通-闪送",
    "银行交易类型": "银联快捷支付",
    "分类标识": "其他支出",
    "交易渠道": "财付通",
    "点进后图标台头": "闪送",
    "type": "支出",
    "balance": 325.22,
    "icon": "其他支出",
    "amount": -36,
    "date": "2019/11/02 12:42:16",
    "ymd": "2019/11/02",
    "time": "12:43:34",
    "abstract": "财付通-腾讯财付通-闪送",
    "title": "闪送",
    "channel": "财付通",
    "dealType": "银联快捷支付"
  },
  {
    "income": 520,
    "expend": 30020.29,
    "hz": "201911"
  },
  {
    "__EMPTY": "2019-09-30T15:59:17.000Z",
    "日期": "2019/10/31 09:24:16",
    "时间": "09:25:57",
    "支出": 30,
    "余额": 393.12,
    "显示摘要": "云视听极光-SNM",
    "银行交易类型": "网联协议支付",
    "分类标识": "休闲娱乐",
    "交易渠道": "财付通",
    "点进后图标台头": "云视听极光-SNM",
    "type": "支出",
    "balance": 393.12,
    "icon": "休闲娱乐",
    "amount": -30,
    "date": "2019/10/31 09:24:16",
    "ymd": "2019/10/31",
    "time": "09:25:57",
    "abstract": "云视听极光-SNM",
    "title": "云视听极光-SNM",
    "channel": "财付通",
    "dealType": "网联协议支付"
  },
  {
    "日期": "2019/10/31 10:18:16",
    "时间": "10:19:00",
    "支出": 200,
    "余额": 423.12,
    "显示摘要": "财付通-微信转账",
    "银行交易类型": "网联协议支付",
    "分类标识": "转账给他人",
    "交易渠道": "财付通",
    "点进后图标台头": "微信转账",
    "type": "支出",
    "balance": 423.12,
    "icon": "转账给他人",
    "amount": -200,
    "date": "2019/10/31 10:18:16",
    "ymd": "2019/10/31",
    "time": "10:19:00",
    "abstract": "财付通-微信转账",
    "title": "微信转账",
    "channel": "财付通",
    "dealType": "网联协议支付"
  },
  {
    "日期": "2019/10/30 20:07:17",
    "时间": "20:08:31",
    "支出": 387,
    "余额": 623.12,
    "显示摘要": "财付通-微信转账",
    "银行交易类型": "网联协议支付",
    "分类标识": "转账给他人",
    "交易渠道": "财付通",
    "点进后图标台头": "微信转账",
    "type": "支出",
    "balance": 623.12,
    "icon": "转账给他人",
    "amount": -387,
    "date": "2019/10/30 20:07:17",
    "ymd": "2019/10/30",
    "time": "20:08:31",
    "abstract": "财付通-微信转账",
    "title": "微信转账",
    "channel": "财付通",
    "dealType": "网联协议支付"
  },
  {
    "日期": "2019/10/28 18:17:16",
    "时间": "18:18:07",
    "支出": 13.5,
    "余额": 1010.12,
    "显示摘要": "财付通-腾讯财付通-真...",
    "银行交易类型": "银联快捷支付",
    "分类标识": "其他支出",
    "交易渠道": "财付通",
    "点进后图标台头": "真好停（北京）信息",
    "type": "支出",
    "balance": 1010.12,
    "icon": "其他支出",
    "amount": -13.5,
    "date": "2019/10/28 18:17:16",
    "ymd": "2019/10/28",
    "time": "18:18:07",
    "abstract": "财付通-腾讯财付通-真...",
    "title": "真好停（北京）信息",
    "channel": "财付通",
    "dealType": "银联快捷支付"
  },
  {
    "日期": "2019/10/28 13:09:16",
    "时间": "13:10:53",
    "支出": 61,
    "余额": 1023.62,
    "显示摘要": "财付通-北京大学第一医院",
    "银行交易类型": "网联协议支付",
    "分类标识": "医疗保健",
    "交易渠道": "财付通",
    "点进后图标台头": "北京大学第一医院",
    "type": "支出",
    "balance": 1023.62,
    "icon": "医疗保健",
    "amount": -61,
    "date": "2019/10/28 13:09:16",
    "ymd": "2019/10/28",
    "time": "13:10:53",
    "abstract": "财付通-北京大学第一医院",
    "title": "北京大学第一医院",
    "channel": "财付通",
    "dealType": "网联协议支付"
  },
  {
    "日期": "2019/10/28 13:04:17",
    "时间": "13:05:07",
    "支出": 60,
    "余额": 1084.62,
    "显示摘要": "财付通-北京大学第一医院",
    "银行交易类型": "网联协议支付",
    "分类标识": "医疗保健",
    "交易渠道": "财付通",
    "点进后图标台头": "北京大学第一医院",
    "type": "支出",
    "balance": 1084.62,
    "icon": "医疗保健",
    "amount": -60,
    "date": "2019/10/28 13:04:17",
    "ymd": "2019/10/28",
    "time": "13:05:07",
    "abstract": "财付通-北京大学第一医院",
    "title": "北京大学第一医院",
    "channel": "财付通",
    "dealType": "网联协议支付"
  },
  {
    "日期": "2019/10/28 10:08:17",
    "时间": "10:09:21",
    "支出": 60,
    "余额": 1144.62,
    "显示摘要": "财付通-北京大学第一医院",
    "银行交易类型": "网联协议支付",
    "分类标识": "医疗保健",
    "交易渠道": "财付通",
    "点进后图标台头": "北京大学第一医院",
    "type": "支出",
    "balance": 1144.62,
    "icon": "医疗保健",
    "amount": -60,
    "date": "2019/10/28 10:08:17",
    "ymd": "2019/10/28",
    "time": "10:09:21",
    "abstract": "财付通-北京大学第一医院",
    "title": "北京大学第一医院",
    "channel": "财付通",
    "dealType": "网联协议支付"
  },
  {
    "日期": "2019/10/28 10:06:17",
    "时间": "10:07:56",
    "收入": 1200,
    "余额": 1204.62,
    "显示摘要": "葛晓君8562转账",
    "银行交易类型": "行内转入",
    "分类标识": "转账给自己",
    "__EMPTY_1": "不计入",
    "点进后图标台头": "葛晓君",
    "type": "收入",
    "balance": 1204.62,
    "icon": "转账给自己",
    "amount": 1200,
    "date": "2019/10/28 10:06:17",
    "ymd": "2019/10/28",
    "time": "10:07:56",
    "abstract": "葛晓君8562转账",
    "title": "葛晓君",
    "dealType": "行内转入"
  },
  {
    "日期": "2019/10/26 20:14:17",
    "时间": "20:15:51",
    "支出": 49.8,
    "余额": 4.62,
    "显示摘要": "财付通-视云影院",
    "银行交易类型": "网联协议支付",
    "分类标识": "休闲娱乐",
    "交易渠道": "财付通",
    "点进后图标台头": "视云影院",
    "type": "支出",
    "balance": 4.62,
    "icon": "休闲娱乐",
    "amount": -49.8,
    "date": "2019/10/26 20:14:17",
    "ymd": "2019/10/26",
    "time": "20:15:51",
    "abstract": "财付通-视云影院",
    "title": "视云影院",
    "channel": "财付通",
    "dealType": "网联协议支付"
  },
  {
    "日期": "2019/10/22 11:20:17",
    "时间": "11:21:19",
    "收入": 9,
    "余额": 54.42,
    "显示摘要": "退 财付通-微信转账",
    "银行交易类型": "网联退款",
    "分类标识": "退款",
    "点进后图标台头": "财付通-微信转账",
    "type": "收入",
    "balance": 54.42,
    "icon": "退款",
    "amount": 9,
    "date": "2019/10/22 11:20:17",
    "ymd": "2019/10/22",
    "time": "11:21:19",
    "abstract": "退 财付通-微信转账",
    "title": "财付通-微信转账",
    "dealType": "网联退款"
  },
  {
    "日期": "2019/10/22 10:50:16",
    "时间": "10:51:00",
    "支出": 9,
    "余额": 45.42,
    "显示摘要": "财付通-微信转账",
    "银行交易类型": "网联协议支付",
    "分类标识": "转账给他人",
    "交易渠道": "财付通",
    "点进后图标台头": "微信转账",
    "type": "支出",
    "balance": 45.42,
    "icon": "转账给他人",
    "amount": -9,
    "date": "2019/10/22 10:50:16",
    "ymd": "2019/10/22",
    "time": "10:51:00",
    "abstract": "财付通-微信转账",
    "title": "微信转账",
    "channel": "财付通",
    "dealType": "网联协议支付"
  },
  {
    "日期": "2019/10/21 16:34:16",
    "时间": "16:35:34",
    "支出": 31,
    "余额": 54.42,
    "显示摘要": "财付通-微信转账",
    "银行交易类型": "网联协议支付",
    "分类标识": "转账给他人",
    "交易渠道": "财付通",
    "点进后图标台头": "微信转账",
    "type": "支出",
    "balance": 54.42,
    "icon": "转账给他人",
    "amount": -31,
    "date": "2019/10/21 16:34:16",
    "ymd": "2019/10/21",
    "time": "16:35:34",
    "abstract": "财付通-微信转账",
    "title": "微信转账",
    "channel": "财付通",
    "dealType": "网联协议支付"
  },
  {
    "日期": "2019/10/21 12:32:17",
    "时间": "12:33:24",
    "支出": 50,
    "余额": 85.42,
    "显示摘要": "财付通-北京一卡通",
    "银行交易类型": "网联协议支付",
    "分类标识": "出行",
    "交易渠道": "财付通",
    "点进后图标台头": "北京一卡通",
    "type": "支出",
    "balance": 85.42,
    "icon": "出行",
    "amount": -50,
    "date": "2019/10/21 12:32:17",
    "ymd": "2019/10/21",
    "time": "12:33:24",
    "abstract": "财付通-北京一卡通",
    "title": "北京一卡通",
    "channel": "财付通",
    "dealType": "网联协议支付"
  },
  {
    "日期": "2019/10/21 12:28:17",
    "时间": "12:29:08",
    "收入": 100,
    "余额": 135.42,
    "显示摘要": "葛晓君8562转账",
    "银行交易类型": "行内转入",
    "分类标识": "转账给自己",
    "__EMPTY_1": "不计入",
    "点进后图标台头": "葛晓君",
    "type": "收入",
    "balance": 135.42,
    "icon": "转账给自己",
    "amount": 100,
    "date": "2019/10/21 12:28:17",
    "ymd": "2019/10/21",
    "time": "12:29:08",
    "abstract": "葛晓君8562转账",
    "title": "葛晓君",
    "dealType": "行内转入"
  },
  {
    "日期": "2019/10/10 19:18:16",
    "时间": "19:19:57",
    "支出": 1272.58,
    "余额": 35.42,
    "显示摘要": "支付宝-花呗",
    "银行交易类型": "网联协议支付",
    "分类标识": "还款",
    "交易渠道": "支付宝",
    "点进后图标台头": "花呗",
    "type": "支出",
    "balance": 35.42,
    "icon": "还款",
    "amount": -1272.58,
    "date": "2019/10/10 19:18:16",
    "ymd": "2019/10/10",
    "time": "19:19:57",
    "abstract": "支付宝-花呗",
    "title": "花呗",
    "channel": "支付宝",
    "dealType": "网联协议支付"
  },
  {
    "日期": "2019/10/10 19:18:16",
    "时间": "19:19:23",
    "收入": 1280,
    "余额": 1308,
    "显示摘要": "葛晓君8562转账",
    "银行交易类型": "行内转入",
    "分类标识": "转账给自己",
    "__EMPTY_1": "不计入",
    "点进后图标台头": "葛晓君",
    "type": "收入",
    "balance": 1308,
    "icon": "转账给自己",
    "amount": 1280,
    "date": "2019/10/10 19:18:16",
    "ymd": "2019/10/10",
    "time": "19:19:23",
    "abstract": "葛晓君8562转账",
    "title": "葛晓君",
    "dealType": "行内转入"
  },
  {
    "日期": "2019/10/09 16:59:16",
    "时间": "17:00:55",
    "支出": 5072,
    "余额": 28,
    "显示摘要": "财付通-微信支付-微...",
    "银行交易类型": "银联快捷支付",
    "分类标识": "转账给他人",
    "交易渠道": "财付通",
    "点进后图标台头": "微信转账",
    "type": "支出",
    "balance": 28,
    "icon": "转账给他人",
    "amount": -5072,
    "date": "2019/10/09 16:59:16",
    "ymd": "2019/10/09",
    "time": "17:00:55",
    "abstract": "财付通-微信支付-微...",
    "title": "微信转账",
    "channel": "财付通",
    "dealType": "银联快捷支付"
  },
  {
    "income": 9,
    "expend": 14487.88,
    "hz": "201910"
  },
  {
    "__EMPTY": "2019-08-31T15:59:17.000Z",
    "日期": "2019/09/30 18:48:17",
    "时间": "18:49:26",
    "支出": 24,
    "余额": 476.38,
    "显示摘要": "财付通-微信转账",
    "银行交易类型": "网联协议支付",
    "分类标识": "转账给他人",
    "交易渠道": "财付通",
    "点进后图标台头": "微信转账",
    "type": "支出",
    "balance": 476.38,
    "icon": "转账给他人",
    "amount": -24,
    "date": "2019/09/30 18:48:17",
    "ymd": "2019/09/30",
    "time": "18:49:26",
    "abstract": "财付通-微信转账",
    "title": "微信转账",
    "channel": "财付通",
    "dealType": "网联协议支付"
  },
  {
    "__EMPTY": "全",
    "日期": "2019/09/30 18:48:17",
    "时间": "18:49:18",
    "支出": 11128,
    "余额": 500.38,
    "显示摘要": "财付通-腾讯财付通-微信...",
    "银行交易类型": "银联快捷支付",
    "分类标识": "转账给他人",
    "交易渠道": "财付通",
    "点进后图标台头": "微信转账",
    "type": "支出",
    "balance": 500.38,
    "icon": "转账给他人",
    "amount": -11128,
    "date": "2019/09/30 18:48:17",
    "ymd": "2019/09/30",
    "time": "18:49:18",
    "abstract": "财付通-腾讯财付通-微信...",
    "title": "微信转账",
    "channel": "财付通",
    "dealType": "银联快捷支付"
  },
  {
    "日期": "2019/09/30 18:31:16",
    "时间": "18:32:02",
    "支出": 200,
    "余额": 11628.38,
    "显示摘要": "财付通-微信转账",
    "银行交易类型": "网联协议支付",
    "分类标识": "转账给他人",
    "交易渠道": "财付通",
    "点进后图标台头": "微信转账",
    "type": "支出",
    "balance": 11628.38,
    "icon": "转账给他人",
    "amount": -200,
    "date": "2019/09/30 18:31:16",
    "ymd": "2019/09/30",
    "time": "18:32:02",
    "abstract": "财付通-微信转账",
    "title": "微信转账",
    "channel": "财付通",
    "dealType": "网联协议支付"
  },
  {
    "日期": "2019/09/30 18:29:16",
    "时间": "18:30:32",
    "收入": 11128,
    "余额": 11828.38,
    "显示摘要": "退 财付通-微信转账",
    "银行交易类型": "网联退款",
    "分类标识": "退款",
    "点进后图标台头": "财付通-微信转账",
    "type": "收入",
    "balance": 11828.38,
    "icon": "退款",
    "amount": 11128,
    "date": "2019/09/30 18:29:16",
    "ymd": "2019/09/30",
    "time": "18:30:32",
    "abstract": "退 财付通-微信转账",
    "title": "财付通-微信转账",
    "dealType": "网联退款"
  },
  {
    "日期": "2019/09/30 18:29:16",
    "时间": "18:30:09",
    "支出": 11128,
    "余额": 700.38,
    "显示摘要": "财付通-微信转账",
    "银行交易类型": "网联协议支付",
    "分类标识": "转账给他人",
    "交易渠道": "财付通",
    "点进后图标台头": "微信转账",
    "type": "支出",
    "balance": 700.38,
    "icon": "转账给他人",
    "amount": -11128,
    "date": "2019/09/30 18:29:16",
    "ymd": "2019/09/30",
    "time": "18:30:09",
    "abstract": "财付通-微信转账",
    "title": "微信转账",
    "channel": "财付通",
    "dealType": "网联协议支付"
  },
  {
    "日期": "2019/09/30 18:28:17",
    "时间": "18:29:08",
    "收入": 11128,
    "余额": 11828.38,
    "显示摘要": "葛晓君8562转账",
    "银行交易类型": "行内转入",
    "分类标识": "转账给自己",
    "__EMPTY_1": "不计入",
    "点进后图标台头": "葛晓君",
    "type": "收入",
    "balance": 11828.38,
    "icon": "转账给自己",
    "amount": 11128,
    "date": "2019/09/30 18:28:17",
    "ymd": "2019/09/30",
    "time": "18:29:08",
    "abstract": "葛晓君8562转账",
    "title": "葛晓君",
    "dealType": "行内转入"
  },
  {
    "日期": "2019/09/30 14:39:16",
    "时间": "14:40:33",
    "支出": 197,
    "余额": 700.38,
    "显示摘要": "财付通-腾讯财付通-微信转账",
    "银行交易类型": "银联快捷支付",
    "分类标识": "转账给他人",
    "交易渠道": "财付通",
    "点进后图标台头": "微信转账",
    "type": "支出",
    "balance": 700.38,
    "icon": "转账给他人",
    "amount": -197,
    "date": "2019/09/30 14:39:16",
    "ymd": "2019/09/30",
    "time": "14:40:33",
    "abstract": "财付通-腾讯财付通-微信转账",
    "title": "微信转账",
    "channel": "财付通",
    "dealType": "银联快捷支付"
  },
  {
    "日期": "2019/09/30 09:45:16",
    "时间": "09:46:22",
    "支出": 30,
    "余额": 897.38,
    "显示摘要": "财付通-云视听极光-SNM",
    "银行交易类型": "网联协议支付",
    "分类标识": "休闲娱乐",
    "交易渠道": "财付通",
    "点进后图标台头": "云视听极光-SNM",
    "type": "支出",
    "balance": 897.38,
    "icon": "休闲娱乐",
    "amount": -30,
    "date": "2019/09/30 09:45:16",
    "ymd": "2019/09/30",
    "time": "09:46:22",
    "abstract": "财付通-云视听极光-SNM",
    "title": "云视听极光-SNM",
    "channel": "财付通",
    "dealType": "网联协议支付"
  },
  {
    "日期": "2019/09/29 17:46:16",
    "时间": "17:47:35",
    "支出": 2700,
    "余额": 927.38,
    "显示摘要": "财付通-腾讯财付通-微信转账",
    "银行交易类型": "银联快捷支付",
    "分类标识": "转账给他人",
    "交易渠道": "财付通",
    "点进后图标台头": "微信转账",
    "type": "支出",
    "balance": 927.38,
    "icon": "转账给他人",
    "amount": -2700,
    "date": "2019/09/29 17:46:16",
    "ymd": "2019/09/29",
    "time": "17:47:35",
    "abstract": "财付通-腾讯财付通-微信转账",
    "title": "微信转账",
    "channel": "财付通",
    "dealType": "银联快捷支付"
  },
  {
    "日期": "2019/09/29 17:45:17",
    "时间": "19:46:02",
    "收入": 3000,
    "余额": 3627.38,
    "显示摘要": "葛晓君8562转账",
    "银行交易类型": "行内转入",
    "分类标识": "转账给自己",
    "__EMPTY_1": "不计入",
    "点进后图标台头": "葛晓君",
    "type": "收入",
    "balance": 3627.38,
    "icon": "转账给自己",
    "amount": 3000,
    "date": "2019/09/29 17:45:17",
    "ymd": "2019/09/29",
    "time": "19:46:02",
    "abstract": "葛晓君8562转账",
    "title": "葛晓君",
    "dealType": "行内转入"
  },
  {
    "日期": "2019/09/28 19:49:17",
    "时间": "19:50:44",
    "支出": 3492,
    "余额": 627.38,
    "显示摘要": "财付通-微信转账",
    "银行交易类型": "网联协议支付",
    "分类标识": "转账给他人",
    "交易渠道": "财付通",
    "点进后图标台头": "微信转账",
    "type": "支出",
    "balance": 627.38,
    "icon": "转账给他人",
    "amount": -3492,
    "date": "2019/09/28 19:49:17",
    "ymd": "2019/09/28",
    "time": "19:50:44",
    "abstract": "财付通-微信转账",
    "title": "微信转账",
    "channel": "财付通",
    "dealType": "网联协议支付"
  },
  {
    "日期": "2019/09/28 19:49:17",
    "时间": "19:50:03",
    "收入": 4000,
    "余额": 4119.38,
    "显示摘要": "葛晓君8562转账",
    "银行交易类型": "行内转入",
    "分类标识": "转账给自己",
    "__EMPTY_1": "不计入",
    "点进后图标台头": "葛晓君",
    "type": "收入",
    "balance": 4119.38,
    "icon": "转账给自己",
    "amount": 4000,
    "date": "2019/09/28 19:49:17",
    "ymd": "2019/09/28",
    "time": "19:50:03",
    "abstract": "葛晓君8562转账",
    "title": "葛晓君",
    "dealType": "行内转入"
  },
  {
    "日期": "2019/09/27 21:09:16",
    "时间": "21:10:30",
    "支出": 49.8,
    "余额": 119.38,
    "显示摘要": "财付通-视云影院",
    "银行交易类型": "网联协议支付",
    "分类标识": "休闲娱乐",
    "交易渠道": "财付通",
    "点进后图标台头": "视云影院",
    "type": "支出",
    "balance": 119.38,
    "icon": "休闲娱乐",
    "amount": -49.8,
    "date": "2019/09/27 21:09:16",
    "ymd": "2019/09/27",
    "time": "21:10:30",
    "abstract": "财付通-视云影院",
    "title": "视云影院",
    "channel": "财付通",
    "dealType": "网联协议支付"
  },
  {
    "日期": "2019/09/27 13:23:16",
    "时间": "13:24:08",
    "支出": 7.5,
    "余额": 169.18,
    "显示摘要": "财付通-腾讯财付通-微信转账",
    "银行交易类型": "银联快捷支付",
    "分类标识": "转账给他人",
    "交易渠道": "财付通",
    "点进后图标台头": "微信转账",
    "type": "支出",
    "balance": 169.18,
    "icon": "转账给他人",
    "amount": -7.5,
    "date": "2019/09/27 13:23:16",
    "ymd": "2019/09/27",
    "time": "13:24:08",
    "abstract": "财付通-腾讯财付通-微信转账",
    "title": "微信转账",
    "channel": "财付通",
    "dealType": "银联快捷支付"
  },
  {
    "日期": "2019/09/27 11:08:16",
    "时间": "11:09:27",
    "支出": 29.9,
    "余额": 176.68,
    "显示摘要": "财付通-微信转账",
    "银行交易类型": "网联协议支付",
    "分类标识": "转账给他人",
    "交易渠道": "财付通",
    "点进后图标台头": "微信转账",
    "type": "支出",
    "balance": 176.68,
    "icon": "转账给他人",
    "amount": -29.9,
    "date": "2019/09/27 11:08:16",
    "ymd": "2019/09/27",
    "time": "11:09:27",
    "abstract": "财付通-微信转账",
    "title": "微信转账",
    "channel": "财付通",
    "dealType": "网联协议支付"
  },
  {
    "日期": "2019/09/26 18:31:16",
    "时间": "18:32:46",
    "支出": 4000,
    "余额": 206.58,
    "显示摘要": "财付通-微信转账",
    "银行交易类型": "网联协议支付",
    "分类标识": "转账给他人",
    "交易渠道": "财付通",
    "点进后图标台头": "微信转账",
    "type": "支出",
    "balance": 206.58,
    "icon": "转账给他人",
    "amount": -4000,
    "date": "2019/09/26 18:31:16",
    "ymd": "2019/09/26",
    "time": "18:32:46",
    "abstract": "财付通-微信转账",
    "title": "微信转账",
    "channel": "财付通",
    "dealType": "网联协议支付"
  },
  {
    "日期": "2019/09/26 18:31:16",
    "时间": "18:32:13",
    "支出": 1000,
    "余额": 4206.58,
    "显示摘要": "财付通-首汽约车",
    "银行交易类型": "网联协议支付",
    "分类标识": "出行",
    "交易渠道": "财付通",
    "点进后图标台头": "首汽约车",
    "type": "支出",
    "balance": 4206.58,
    "icon": "出行",
    "amount": -1000,
    "date": "2019/09/26 18:31:16",
    "ymd": "2019/09/26",
    "time": "18:32:13",
    "abstract": "财付通-首汽约车",
    "title": "首汽约车",
    "channel": "财付通",
    "dealType": "网联协议支付"
  },
  {
    "日期": "2019/09/26 18:30:17",
    "时间": "18:31:21",
    "收入": 5000,
    "余额": 5206.58,
    "显示摘要": "葛晓君8562转账",
    "银行交易类型": "行内转入",
    "分类标识": "转账给自己",
    "__EMPTY_1": "不计入",
    "点进后图标台头": "葛晓君",
    "type": "收入",
    "balance": 5206.58,
    "icon": "转账给自己",
    "amount": 5000,
    "date": "2019/09/26 18:30:17",
    "ymd": "2019/09/26",
    "time": "18:31:21",
    "abstract": "葛晓君8562转账",
    "title": "葛晓君",
    "dealType": "行内转入"
  },
  {
    "日期": "2019/09/25 12:23:17",
    "时间": "12:24:45",
    "支出": 11000,
    "余额": 206.58,
    "显示摘要": "财付通-微信转账",
    "银行交易类型": "网联协议支付",
    "分类标识": "转账给他人",
    "交易渠道": "财付通",
    "点进后图标台头": "微信转账",
    "type": "支出",
    "balance": 206.58,
    "icon": "转账给他人",
    "amount": -11000,
    "date": "2019/09/25 12:23:17",
    "ymd": "2019/09/25",
    "time": "12:24:45",
    "abstract": "财付通-微信转账",
    "title": "微信转账",
    "channel": "财付通",
    "dealType": "网联协议支付"
  },
  {
    "日期": "2019/09/25 12:22:16",
    "时间": "12:23:49",
    "收入": 11000,
    "余额": 11206.58,
    "显示摘要": "葛晓君8562转账",
    "银行交易类型": "行内转入",
    "分类标识": "转账给自己",
    "__EMPTY_1": "不计入",
    "点进后图标台头": "葛晓君",
    "type": "收入",
    "balance": 11206.58,
    "icon": "转账给自己",
    "amount": 11000,
    "date": "2019/09/25 12:22:16",
    "ymd": "2019/09/25",
    "time": "12:23:49",
    "abstract": "葛晓君8562转账",
    "title": "葛晓君",
    "dealType": "行内转入"
  },
  {
    "日期": "2019/09/24 11:40:17",
    "时间": "11:41:48",
    "支出": 300,
    "余额": 206.58,
    "显示摘要": "财付通-国网北京电力",
    "银行交易类型": "网联协议支付",
    "分类标识": "充值缴费",
    "交易渠道": "财付通",
    "点进后图标台头": "国网北京电力",
    "type": "支出",
    "balance": 206.58,
    "icon": "充值缴费",
    "amount": -300,
    "date": "2019/09/24 11:40:17",
    "ymd": "2019/09/24",
    "time": "11:41:48",
    "abstract": "财付通-国网北京电力",
    "title": "国网北京电力",
    "channel": "财付通",
    "dealType": "网联协议支付"
  },
  {
    "__EMPTY": "****",
    "日期": "2019/09/24 11:39:16",
    "时间": "11:40:03",
    "支出": 3500,
    "余额": 506.58,
    "显示摘要": "银联消费玛俪琳商贸...",
    "银行交易类型": "银联POS消费",
    "分类标识": "其他支出",
    "交易渠道": "无",
    "点进后图标台头": "玛俪琳商贸有限公司朝阳分*",
    "type": "支出",
    "balance": 506.58,
    "icon": "其他支出",
    "amount": -3500,
    "date": "2019/09/24 11:39:16",
    "ymd": "2019/09/24",
    "time": "11:40:03",
    "abstract": "银联消费玛俪琳商贸...",
    "title": "玛俪琳商贸有限公司朝阳分*",
    "channel": "无",
    "dealType": "银联POS消费"
  },
  {
    "日期": "2019/09/21 15:18:16",
    "时间": "15:19:33",
    "支出": 39.9,
    "余额": 4006.58,
    "显示摘要": "财付通-微信转账",
    "银行交易类型": "网联协议支付",
    "分类标识": "转账给他人",
    "交易渠道": "财付通",
    "点进后图标台头": "微信转账",
    "type": "支出",
    "balance": 4006.58,
    "icon": "转账给他人",
    "amount": -39.9,
    "date": "2019/09/21 15:18:16",
    "ymd": "2019/09/21",
    "time": "15:19:33",
    "abstract": "财付通-微信转账",
    "title": "微信转账",
    "channel": "财付通",
    "dealType": "网联协议支付"
  },
  {
    "日期": "2019/09/21 15:06:16",
    "时间": "15:07:39",
    "支出": 67.7,
    "余额": 4046.48,
    "显示摘要": "财付通-京东商城平台商户",
    "银行交易类型": "网联协议支付",
    "分类标识": "购物",
    "交易渠道": "财付通",
    "点进后图标台头": "京东商城平台商户",
    "type": "支出",
    "balance": 4046.48,
    "icon": "购物",
    "amount": -67.7,
    "date": "2019/09/21 15:06:16",
    "ymd": "2019/09/21",
    "time": "15:07:39",
    "abstract": "财付通-京东商城平台商户",
    "title": "京东商城平台商户",
    "channel": "财付通",
    "dealType": "网联协议支付"
  },
  {
    "日期": "2019/09/21 02:37:16",
    "时间": "02:38:33",
    "收入": 0.77,
    "余额": 4114.18,
    "显示摘要": "结息：0.77扣税：0.00",
    "银行交易类型": "账户结息",
    "分类标识": "投资收益",
    "点进后图标台头": "结息：0.77扣税：0.00",
    "type": "收入",
    "balance": 4114.18,
    "icon": "投资收益",
    "amount": 0.77,
    "date": "2019/09/21 02:37:16",
    "ymd": "2019/09/21",
    "time": "02:38:33",
    "abstract": "结息：0.77扣税：0.00",
    "title": "结息：0.77扣税：0.00",
    "dealType": "账户结息"
  },
  {
    "__EMPTY": "重点条目",
    "日期": "2019/09/17 18:44:17",
    "时间": "18:45:21",
    "支出": 44500,
    "余额": 4113.41,
    "显示摘要": "北京市朝阳区石器时代...",
    "银行交易类型": "银联POS消费",
    "分类标识": "餐饮",
    "交易渠道": "无",
    "点进后图标台头": "北京市朝阳区石器时代（双井店）餐饮店",
    "type": "支出",
    "balance": 4113.41,
    "icon": "餐饮",
    "amount": -44500,
    "date": "2019/09/17 18:44:17",
    "ymd": "2019/09/17",
    "time": "18:45:21",
    "abstract": "北京市朝阳区石器时代...",
    "title": "北京市朝阳区石器时代（双井店）餐饮店",
    "channel": "无",
    "dealType": "银联POS消费"
  },
  {
    "日期": "2019/09/16 12:46:17",
    "时间": "Invalid date",
    "支出": 1999.13,
    "余额": 48613.41,
    "显示摘要": "支付宝-花呗",
    "银行交易类型": "网联协议支付",
    "分类标识": "还款",
    "交易渠道": "支付宝",
    "点进后图标台头": "花呗",
    "type": "支出",
    "balance": 48613.41,
    "icon": "还款",
    "amount": -1999.13,
    "date": "2019/09/16 12:46:17",
    "ymd": "2019/09/16",
    "time": "Invalid date",
    "abstract": "支付宝-花呗",
    "title": "花呗",
    "channel": "支付宝",
    "dealType": "网联协议支付"
  },
  {
    "__EMPTY": "****",
    "日期": "2019/09/15 13:44:17",
    "时间": "13:45:31",
    "支出": 536.4,
    "余额": 50612.54,
    "显示摘要": "银联消费华润超级市场...",
    "银行交易类型": "银联POS消费",
    "分类标识": "购物",
    "交易渠道": "无",
    "点进后图标台头": "华润超级市场有限公司",
    "type": "支出",
    "balance": 50612.54,
    "icon": "购物",
    "amount": -536.4,
    "date": "2019/09/15 13:44:17",
    "ymd": "2019/09/15",
    "time": "13:45:31",
    "abstract": "银联消费华润超级市场...",
    "title": "华润超级市场有限公司",
    "channel": "无",
    "dealType": "银联POS消费"
  },
  {
    "日期": "2019/09/11 22:34:16",
    "时间": "22:35:07",
    "支出": 750,
    "余额": 51148.94,
    "显示摘要": "支付宝-特约商户",
    "银行交易类型": "网联协议支付",
    "分类标识": "其他支出",
    "交易渠道": "支付宝",
    "点进后图标台头": "特约商户",
    "type": "支出",
    "balance": 51148.94,
    "icon": "其他支出",
    "amount": -750,
    "date": "2019/09/11 22:34:16",
    "ymd": "2019/09/11",
    "time": "22:35:07",
    "abstract": "支付宝-特约商户",
    "title": "特约商户",
    "channel": "支付宝",
    "dealType": "网联协议支付"
  },
  {
    "日期": "2019/09/11 17:38:17",
    "时间": "17:39:41",
    "支出": 447.6,
    "余额": 51898.94,
    "显示摘要": "财付通-微信转账",
    "分类标识": "转账给他人",
    "交易渠道": "财付通",
    "点进后图标台头": "微信转账",
    "type": "支出",
    "balance": 51898.94,
    "icon": "转账给他人",
    "amount": -447.6,
    "date": "2019/09/11 17:38:17",
    "ymd": "2019/09/11",
    "time": "17:39:41",
    "abstract": "财付通-微信转账",
    "title": "微信转账",
    "channel": "财付通"
  },
  {
    "__EMPTY": "****",
    "日期": "2019/09/11 11:37:16",
    "时间": "11:38:34",
    "收入": 4090,
    "余额": 52346.54,
    "显示摘要": "马骥0002转账",
    "银行交易类型": "行内转入",
    "分类标识": "他人转入",
    "交易渠道": "招商银行",
    "点进后图标台头": "马骥",
    "type": "收入",
    "balance": 52346.54,
    "icon": "他人转入",
    "amount": 4090,
    "date": "2019/09/11 11:37:16",
    "ymd": "2019/09/11",
    "time": "11:38:34",
    "abstract": "马骥0002转账",
    "title": "马骥",
    "channel": "招商银行",
    "dealType": "行内转入"
  },
  {
    "日期": "2019/09/10 17:20:17",
    "时间": "17:21:31",
    "支出": 2834.9,
    "余额": 48346.54,
    "显示摘要": "财付通-腾讯财付通-中山市",
    "银行交易类型": "银联快捷支付",
    "分类标识": "其他支出",
    "交易渠道": "财付通",
    "点进后图标台头": "中山市海德東方物业",
    "type": "支出",
    "balance": 48346.54,
    "icon": "其他支出",
    "amount": -2834.9,
    "date": "2019/09/10 17:20:17",
    "ymd": "2019/09/10",
    "time": "17:21:31",
    "abstract": "财付通-腾讯财付通-中山市",
    "title": "中山市海德東方物业",
    "channel": "财付通",
    "dealType": "银联快捷支付"
  },
  {
    "日期": "2019/09/08 15:49:16",
    "时间": "15:50:42",
    "支出": 1261.77,
    "余额": 51181.44,
    "显示摘要": "支付宝-花呗",
    "银行交易类型": "网联协议支付",
    "分类标识": "还款",
    "交易渠道": "支付宝",
    "点进后图标台头": "花呗",
    "type": "支出",
    "balance": 51181.44,
    "icon": "还款",
    "amount": -1261.77,
    "date": "2019/09/08 15:49:16",
    "ymd": "2019/09/08",
    "time": "15:50:42",
    "abstract": "支付宝-花呗",
    "title": "花呗",
    "channel": "支付宝",
    "dealType": "网联协议支付"
  },
  {
    "日期": "2019/09/07 11:05:17",
    "时间": "11:06:35",
    "支出": 200,
    "余额": 52443.21,
    "显示摘要": "财付通-微信转账",
    "银行交易类型": "网联协议支付",
    "分类标识": "转账给他人",
    "交易渠道": "财付通",
    "点进后图标台头": "微信转账",
    "type": "支出",
    "balance": 52443.21,
    "icon": "转账给他人",
    "amount": -200,
    "date": "2019/09/07 11:05:17",
    "ymd": "2019/09/07",
    "time": "11:06:35",
    "abstract": "财付通-微信转账",
    "title": "微信转账",
    "channel": "财付通",
    "dealType": "网联协议支付"
  },
  {
    "日期": "2019/09/05 21:05:17",
    "时间": "21:06:04",
    "支出": 696,
    "余额": 52643.21,
    "显示摘要": "财付通-微信转账",
    "银行交易类型": "网联协议支付",
    "分类标识": "转账给他人",
    "交易渠道": "财付通",
    "点进后图标台头": "微信转账",
    "type": "支出",
    "balance": 52643.21,
    "icon": "转账给他人",
    "amount": -696,
    "date": "2019/09/05 21:05:17",
    "ymd": "2019/09/05",
    "time": "21:06:04",
    "abstract": "财付通-微信转账",
    "title": "微信转账",
    "channel": "财付通",
    "dealType": "网联协议支付"
  },
  {
    "日期": "2019/09/05 18:26:17",
    "时间": "18:27:34",
    "支出": 300,
    "余额": 53339.21,
    "显示摘要": "财付通-腾讯财付通-微信转账",
    "银行交易类型": "银联快捷支付",
    "分类标识": "转账给他人",
    "交易渠道": "财付通",
    "点进后图标台头": "微信转账",
    "type": "支出",
    "balance": 53339.21,
    "icon": "转账给他人",
    "amount": -300,
    "date": "2019/09/05 18:26:17",
    "ymd": "2019/09/05",
    "time": "18:27:34",
    "abstract": "财付通-腾讯财付通-微信转账",
    "title": "微信转账",
    "channel": "财付通",
    "dealType": "银联快捷支付"
  },
  {
    "日期": "2019/09/02 21:19:17",
    "时间": "21:20:23",
    "支出": 198.8,
    "余额": 53639.21,
    "显示摘要": "财付通-京东商城平台商户",
    "银行交易类型": "网联协议支付",
    "分类标识": "购物",
    "交易渠道": "财付通",
    "点进后图标台头": "京东商城平台商户",
    "type": "支出",
    "balance": 53639.21,
    "icon": "购物",
    "amount": -198.8,
    "date": "2019/09/02 21:19:17",
    "ymd": "2019/09/02",
    "time": "21:20:23",
    "abstract": "财付通-京东商城平台商户",
    "title": "京东商城平台商户",
    "channel": "财付通",
    "dealType": "网联协议支付"
  },
  {
    "日期": "2019/09/02 20:41:17",
    "时间": "20:42:46",
    "支出": 199.8,
    "余额": 53838.01,
    "显示摘要": "财付通-手机充值",
    "银行交易类型": "网联协议支付",
    "分类标识": "充值缴费",
    "交易渠道": "财付通",
    "点进后图标台头": "手机充值",
    "type": "支出",
    "balance": 53838.01,
    "icon": "充值缴费",
    "amount": -199.8,
    "date": "2019/09/02 20:41:17",
    "ymd": "2019/09/02",
    "time": "20:42:46",
    "abstract": "财付通-手机充值",
    "title": "手机充值",
    "channel": "财付通",
    "dealType": "网联协议支付"
  },
  {
    "日期": "2019/09/01 15:28:17",
    "时间": "15:29:36",
    "支出": 3000,
    "余额": 54037.81,
    "显示摘要": "财付通-微信转账",
    "银行交易类型": "网联协议支付",
    "分类标识": "转账给他人",
    "交易渠道": "财付通",
    "点进后图标台头": "微信转账",
    "type": "支出",
    "balance": 54037.81,
    "icon": "转账给他人",
    "amount": -3000,
    "date": "2019/09/01 15:28:17",
    "ymd": "2019/09/01",
    "time": "15:29:36",
    "abstract": "财付通-微信转账",
    "title": "微信转账",
    "channel": "财付通",
    "dealType": "网联协议支付"
  },
  {
    "日期": "2019/09/01 13:48:16",
    "时间": "13:49:09",
    "收入": 51984,
    "余额": 57037.81,
    "显示摘要": "史新华0655转账",
    "银行交易类型": "汇入汇款",
    "分类标识": "他人转入",
    "交易渠道": "平安银行股份有限公司",
    "点进后图标台头": "史新华",
    "type": "收入",
    "balance": 57037.81,
    "icon": "他人转入",
    "amount": 51984,
    "date": "2019/09/01 13:48:16",
    "ymd": "2019/09/01",
    "time": "13:49:09",
    "abstract": "史新华0655转账",
    "title": "史新华",
    "channel": "平安银行股份有限公司",
    "dealType": "汇入汇款"
  },
  {
    "income": 67202.77,
    "expend": 83562.2,
    "hz": "20199"
  },
  {
    "__EMPTY": "2019-07-31T15:59:17.000Z",
    "日期": "2019/08/28 15:36:16",
    "时间": "15:37:06",
    "收入": 4000,
    "余额": 5053.81,
    "显示摘要": "史新华0655跨行转账",
    "银行交易类型": "汇入汇款",
    "分类标识": "他人转入",
    "交易渠道": "平安银行股份有限公司",
    "__EMPTY_1": "不计入",
    "点进后图标台头": "史新华",
    "type": "收入",
    "balance": 5053.81,
    "icon": "他人转入",
    "amount": 4000,
    "date": "2019/08/28 15:36:16",
    "ymd": "2019/08/28",
    "time": "15:37:06",
    "abstract": "史新华0655跨行转账",
    "title": "史新华",
    "channel": "平安银行股份有限公司",
    "dealType": "汇入汇款"
  },
  {
    "__EMPTY": "全",
    "日期": "2019/08/21 11:20:17",
    "时间": "11:21:00",
    "收入": 1000,
    "余额": 1053.81,
    "显示摘要": "史新华0655跨行转账",
    "银行交易类型": "汇入汇款",
    "分类标识": "他人转入",
    "交易渠道": "平安银行股份有限公司",
    "__EMPTY_1": "不计入",
    "点进后图标台头": "史新华",
    "type": "收入",
    "balance": 1053.81,
    "icon": "他人转入",
    "amount": 1000,
    "date": "2019/08/21 11:20:17",
    "ymd": "2019/08/21",
    "time": "11:21:00",
    "abstract": "史新华0655跨行转账",
    "title": "史新华",
    "channel": "平安银行股份有限公司",
    "dealType": "汇入汇款"
  },
  {
    "日期": "2019/08/12 13:21:16",
    "时间": "13:22:48",
    "支出": 446.19,
    "余额": 53.81,
    "显示摘要": "支付宝-花呗",
    "银行交易类型": "网联协议支付",
    "分类标识": "还款",
    "交易渠道": "支付宝",
    "点进后图标台头": "花呗",
    "type": "支出",
    "balance": 53.81,
    "icon": "还款",
    "amount": -446.19,
    "date": "2019/08/12 13:21:16",
    "ymd": "2019/08/12",
    "time": "13:22:48",
    "abstract": "支付宝-花呗",
    "title": "花呗",
    "channel": "支付宝",
    "dealType": "网联协议支付"
  },
  {
    "日期": "2019/08/12 13:19:17",
    "时间": "13:20:59",
    "收入": 500,
    "余额": 500,
    "显示摘要": "葛晓君8562转账",
    "银行交易类型": "行内转入",
    "分类标识": "转账给自己",
    "__EMPTY_1": "不计入",
    "点进后图标台头": "葛晓君",
    "type": "收入",
    "balance": 500,
    "icon": "转账给自己",
    "amount": 500,
    "date": "2019/08/12 13:19:17",
    "ymd": "2019/08/12",
    "time": "13:20:59",
    "abstract": "葛晓君8562转账",
    "title": "葛晓君",
    "dealType": "行内转入"
  },
  {
    "日期": "2019/08/08 18:23:17",
    "时间": "18:24:28",
    "支出": 66.35,
    "余额": 0,
    "显示摘要": "20190808A0011001...",
    "银行交易类型": "信用卡存款",
    "分类标识": "还招行信用卡",
    "点进后图标台头": "20190808A0011001",
    "type": "支出",
    "balance": 0,
    "icon": "还招行信用卡",
    "amount": -66.35,
    "date": "2019/08/08 18:23:17",
    "ymd": "2019/08/08",
    "time": "18:24:28",
    "abstract": "20190808A0011001...",
    "title": "20190808A0011001",
    "dealType": "信用卡存款"
  },
  {
    "日期": "2019/08/04 10:49:17",
    "时间": "10:50:52",
    "支出": 150,
    "余额": 66.35,
    "显示摘要": "财付通-微信转账",
    "银行交易类型": "网联协议支付",
    "分类标识": "转账给他人",
    "交易渠道": "财付通",
    "点进后图标台头": "微信转账",
    "type": "支出",
    "balance": 66.35,
    "icon": "转账给他人",
    "amount": -150,
    "date": "2019/08/04 10:49:17",
    "ymd": "2019/08/04",
    "time": "10:50:52",
    "abstract": "财付通-微信转账",
    "title": "微信转账",
    "channel": "财付通",
    "dealType": "网联协议支付"
  },
  {
    "日期": "2019/08/01 14:37:16",
    "时间": "14:38:31",
    "支出": 1000,
    "余额": 216.35,
    "显示摘要": "财付通-首汽约车",
    "银行交易类型": "网联协议支付",
    "分类标识": "出行",
    "交易渠道": "财付通",
    "点进后图标台头": "首汽约车",
    "type": "支出",
    "balance": 216.35,
    "icon": "出行",
    "amount": -1000,
    "date": "2019/08/01 14:37:16",
    "ymd": "2019/08/01",
    "time": "14:38:31",
    "abstract": "财付通-首汽约车",
    "title": "首汽约车",
    "channel": "财付通",
    "dealType": "网联协议支付"
  },
  {
    "日期": "2019/08/01 14:15:16",
    "时间": "14:16:34",
    "收入": 1000,
    "余额": 1216.35,
    "显示摘要": "葛晓君8562转账",
    "银行交易类型": "行内转入",
    "分类标识": "转账给自己",
    "__EMPTY_1": "不计入",
    "点进后图标台头": "葛晓君",
    "type": "收入",
    "balance": 1216.35,
    "icon": "转账给自己",
    "amount": 1000,
    "date": "2019/08/01 14:15:16",
    "ymd": "2019/08/01",
    "time": "14:16:34",
    "abstract": "葛晓君8562转账",
    "title": "葛晓君",
    "dealType": "行内转入"
  },
  {
    "income": 0,
    "expend": 1596.19,
    "hz": "20198"
  },
  {
    "__EMPTY": "2019-06-30T15:59:17.000Z",
    "日期": "2019/07/29 15:35:17",
    "时间": "15:36:38",
    "支出": 273.65,
    "余额": 216.35,
    "显示摘要": "财付通-北京市医院管理...",
    "银行交易类型": "网联协议支付",
    "分类标识": "医疗保健",
    "交易渠道": "财付通",
    "点进后图标台头": "北京市医院管理中心",
    "type": "支出",
    "balance": 216.35,
    "icon": "医疗保健",
    "amount": -273.65,
    "date": "2019/07/29 15:35:17",
    "ymd": "2019/07/29",
    "time": "15:36:38",
    "abstract": "财付通-北京市医院管理...",
    "title": "北京市医院管理中心",
    "channel": "财付通",
    "dealType": "网联协议支付"
  },
  {
    "日期": "2019/07/25 16:20:17",
    "时间": "16:21:39",
    "支出": 2588,
    "余额": 490,
    "显示摘要": "财付通-微信转账",
    "银行交易类型": "网联协议支付",
    "分类标识": "转账给他人",
    "交易渠道": "财付通",
    "点进后图标台头": "微信转账",
    "type": "支出",
    "balance": 490,
    "icon": "转账给他人",
    "amount": -2588,
    "date": "2019/07/25 16:20:17",
    "ymd": "2019/07/25",
    "time": "16:21:39",
    "abstract": "财付通-微信转账",
    "title": "微信转账",
    "channel": "财付通",
    "dealType": "网联协议支付"
  },
  {
    "日期": "2019/07/25 12:02:16",
    "时间": "12:03:38",
    "收入": 3000,
    "余额": 3078,
    "显示摘要": "葛晓君8562转账",
    "银行交易类型": "行内转入",
    "分类标识": "转账给自己",
    "__EMPTY_1": "不计入",
    "点进后图标台头": "葛晓君",
    "type": "收入",
    "balance": 3078,
    "icon": "转账给自己",
    "amount": 3000,
    "date": "2019/07/25 12:02:16",
    "ymd": "2019/07/25",
    "time": "12:03:38",
    "abstract": "葛晓君8562转账",
    "title": "葛晓君",
    "dealType": "行内转入"
  },
  {
    "日期": "2019/07/23 19:25:16",
    "时间": "19:26:12",
    "支出": 11600,
    "余额": 78,
    "显示摘要": "财付通-微信转账",
    "银行交易类型": "网联协议支付",
    "分类标识": "转账给他人",
    "交易渠道": "财付通",
    "点进后图标台头": "微信转账",
    "type": "支出",
    "balance": 78,
    "icon": "转账给他人",
    "amount": -11600,
    "date": "2019/07/23 19:25:16",
    "ymd": "2019/07/23",
    "time": "19:26:12",
    "abstract": "财付通-微信转账",
    "title": "微信转账",
    "channel": "财付通",
    "dealType": "网联协议支付"
  },
  {
    "日期": "2019/07/23 19:24:17",
    "时间": "19:25:57",
    "收入": 9000,
    "余额": 11678,
    "显示摘要": "葛晓君8562转账",
    "银行交易类型": "行内转入",
    "分类标识": "转账给自己",
    "__EMPTY_1": "不计入",
    "点进后图标台头": "葛晓君",
    "type": "收入",
    "balance": 11678,
    "icon": "转账给自己",
    "amount": 9000,
    "date": "2019/07/23 19:24:17",
    "ymd": "2019/07/23",
    "time": "19:25:57",
    "abstract": "葛晓君8562转账",
    "title": "葛晓君",
    "dealType": "行内转入"
  },
  {
    "__EMPTY": "重点条目",
    "日期": "2019/07/22 16:02:16",
    "时间": "16:03:26",
    "支出": 15960,
    "余额": 2678,
    "显示摘要": "北京南门涮肉餐饮管理有限...",
    "银行交易类型": "银联POS消费",
    "分类标识": "餐饮",
    "交易渠道": "无",
    "点进后图标台头": "北京南门涮肉餐饮管理有限公司",
    "type": "支出",
    "balance": 2678,
    "icon": "餐饮",
    "amount": -15960,
    "date": "2019/07/22 16:02:16",
    "ymd": "2019/07/22",
    "time": "16:03:26",
    "abstract": "北京南门涮肉餐饮管理有限...",
    "title": "北京南门涮肉餐饮管理有限公司",
    "channel": "无",
    "dealType": "银联POS消费"
  },
  {
    "日期": "2019/07/21 11:07:17",
    "时间": "11:08:44",
    "支出": 29,
    "余额": 18638,
    "显示摘要": "财付通-国广东方",
    "银行交易类型": "网联协议支付",
    "分类标识": "充值缴费",
    "交易渠道": "财付通",
    "点进后图标台头": "国广东方",
    "type": "支出",
    "balance": 18638,
    "icon": "充值缴费",
    "amount": -29,
    "date": "2019/07/21 11:07:17",
    "ymd": "2019/07/21",
    "time": "11:08:44",
    "abstract": "财付通-国广东方",
    "title": "国广东方",
    "channel": "财付通",
    "dealType": "网联协议支付"
  },
  {
    "日期": "2019/07/21 11:05:17",
    "时间": "11:06:38",
    "支出": 16,
    "余额": 18667,
    "显示摘要": "财付通-国广东方",
    "银行交易类型": "网联协议支付",
    "分类标识": "充值缴费",
    "交易渠道": "财付通",
    "点进后图标台头": "国广东方",
    "type": "支出",
    "balance": 18667,
    "icon": "充值缴费",
    "amount": -16,
    "date": "2019/07/21 11:05:17",
    "ymd": "2019/07/21",
    "time": "11:06:38",
    "abstract": "财付通-国广东方",
    "title": "国广东方",
    "channel": "财付通",
    "dealType": "网联协议支付"
  },
  {
    "日期": "2019/07/18 23:05:17",
    "时间": "23:06:33",
    "支出": 725,
    "余额": 18683,
    "显示摘要": "财付通-微信转账",
    "银行交易类型": "网联协议支付",
    "分类标识": "转账给他人",
    "交易渠道": "财付通",
    "点进后图标台头": "微信转账",
    "type": "支出",
    "balance": 18683,
    "icon": "转账给他人",
    "amount": -725,
    "date": "2019/07/18 23:05:17",
    "ymd": "2019/07/18",
    "time": "23:06:33",
    "abstract": "财付通-微信转账",
    "title": "微信转账",
    "channel": "财付通",
    "dealType": "网联协议支付"
  },
  {
    "日期": "2019/07/18 21:08:16",
    "时间": "21:09:12",
    "支出": 2000,
    "余额": 19408,
    "显示摘要": "财付通-首汽约车",
    "银行交易类型": "网联协议支付",
    "分类标识": "出行",
    "交易渠道": "财付通",
    "点进后图标台头": "首汽约车",
    "type": "支出",
    "balance": 19408,
    "icon": "出行",
    "amount": -2000,
    "date": "2019/07/18 21:08:16",
    "ymd": "2019/07/18",
    "time": "21:09:12",
    "abstract": "财付通-首汽约车",
    "title": "首汽约车",
    "channel": "财付通",
    "dealType": "网联协议支付"
  },
  {
    "日期": "2019/07/18 17:07:17",
    "时间": "17:08:25",
    "支出": 11290,
    "余额": 21408,
    "显示摘要": "银联消费金美仕贸易有限公...",
    "银行交易类型": "银联POS消费",
    "分类标识": "其他支出",
    "交易渠道": "无",
    "点进后图标台头": "金美仕贸易有限公司",
    "type": "支出",
    "balance": 21408,
    "icon": "其他支出",
    "amount": -11290,
    "date": "2019/07/18 17:07:17",
    "ymd": "2019/07/18",
    "time": "17:08:25",
    "abstract": "银联消费金美仕贸易有限公...",
    "title": "金美仕贸易有限公司",
    "channel": "无",
    "dealType": "银联POS消费"
  },
  {
    "日期": "2019/07/17 21:43:17",
    "时间": "21:44:05",
    "支出": 600,
    "余额": 32698,
    "显示摘要": "财付通-微信转账",
    "银行交易类型": "网联协议支付",
    "分类标识": "转账给他人",
    "交易渠道": "财付通",
    "点进后图标台头": "微信转账",
    "type": "支出",
    "balance": 32698,
    "icon": "转账给他人",
    "amount": -600,
    "date": "2019/07/17 21:43:17",
    "ymd": "2019/07/17",
    "time": "21:44:05",
    "abstract": "财付通-微信转账",
    "title": "微信转账",
    "channel": "财付通",
    "dealType": "网联协议支付"
  },
  {
    "日期": "2019/07/17 18:11:16",
    "时间": "18:12:16",
    "支出": 876.3,
    "余额": 33298,
    "显示摘要": "银联消费华润超级市场...",
    "银行交易类型": "银联POS消费",
    "分类标识": "购物",
    "交易渠道": "无",
    "点进后图标台头": "华润超级市场有限公司",
    "type": "支出",
    "balance": 33298,
    "icon": "购物",
    "amount": -876.3,
    "date": "2019/07/17 18:11:16",
    "ymd": "2019/07/17",
    "time": "18:12:16",
    "abstract": "银联消费华润超级市场...",
    "title": "华润超级市场有限公司",
    "channel": "无",
    "dealType": "银联POS消费"
  },
  {
    "日期": "2019/07/12 22:16:16",
    "时间": "22:17:04",
    "支出": 132,
    "余额": 34174.3,
    "显示摘要": "财付通-微信转账",
    "银行交易类型": "网联协议支付",
    "分类标识": "转账给他人",
    "交易渠道": "财付通",
    "点进后图标台头": "微信转账",
    "type": "支出",
    "balance": 34174.3,
    "icon": "转账给他人",
    "amount": -132,
    "date": "2019/07/12 22:16:16",
    "ymd": "2019/07/12",
    "time": "22:17:04",
    "abstract": "财付通-微信转账",
    "title": "微信转账",
    "channel": "财付通",
    "dealType": "网联协议支付"
  },
  {
    "日期": "2019/07/12 20:06:16",
    "时间": "20:07:41",
    "收入": 10000,
    "余额": 34306.3,
    "显示摘要": "王翰泽0088转账",
    "银行交易类型": "行内转入",
    "分类标识": "他人转入",
    "交易渠道": "招商银行",
    "点进后图标台头": "王翰泽",
    "__EMPTY_2": "招商银行",
    "__EMPTY_3": "6214********0088",
    "type": "收入",
    "balance": 34306.3,
    "icon": "他人转入",
    "amount": 10000,
    "date": "2019/07/12 20:06:16",
    "ymd": "2019/07/12",
    "time": "20:07:41",
    "abstract": "王翰泽0088转账",
    "title": "王翰泽",
    "channel": "招商银行",
    "dealType": "行内转入"
  },
  {
    "日期": "2019/07/09 14:48:16",
    "时间": "14:49:36",
    "支出": 2162,
    "余额": 24306.3,
    "显示摘要": "财付通-微信转账",
    "银行交易类型": "网联协议支付",
    "分类标识": "转账给他人",
    "交易渠道": "财付通",
    "点进后图标台头": "微信转账",
    "type": "支出",
    "balance": 24306.3,
    "icon": "转账给他人",
    "amount": -2162,
    "date": "2019/07/09 14:48:16",
    "ymd": "2019/07/09",
    "time": "14:49:36",
    "abstract": "财付通-微信转账",
    "title": "微信转账",
    "channel": "财付通",
    "dealType": "网联协议支付"
  },
  {
    "日期": "2019/07/09 13:33:17",
    "时间": "13:34:21",
    "支出": 500,
    "余额": 26468.3,
    "显示摘要": "银联消费中国石油",
    "银行交易类型": "银联POS消费",
    "分类标识": "私家车",
    "交易渠道": "无",
    "点进后图标台头": "中国石油",
    "type": "支出",
    "balance": 26468.3,
    "icon": "私家车",
    "amount": -500,
    "date": "2019/07/09 13:33:17",
    "ymd": "2019/07/09",
    "time": "13:34:21",
    "abstract": "银联消费中国石油",
    "title": "中国石油",
    "channel": "无",
    "dealType": "银联POS消费"
  },
  {
    "日期": "2019/07/08 17:55:16",
    "时间": "17:56:29",
    "支出": 1618.49,
    "余额": 26968.3,
    "显示摘要": "20190708A0011001...",
    "银行交易类型": "信用卡存款",
    "分类标识": "还招行信用卡",
    "__EMPTY_1": "不计入",
    "点进后图标台头": "20190708A0011001",
    "type": "支出",
    "balance": 26968.3,
    "icon": "还招行信用卡",
    "amount": -1618.49,
    "date": "2019/07/08 17:55:16",
    "ymd": "2019/07/08",
    "time": "17:56:29",
    "abstract": "20190708A0011001...",
    "title": "20190708A0011001",
    "dealType": "信用卡存款"
  },
  {
    "日期": "2019/07/05 21:25:17",
    "时间": "21:26:18",
    "支出": 2487,
    "余额": 28586.79,
    "显示摘要": "财付通-微信转账",
    "银行交易类型": "网联协议支付",
    "分类标识": "转账给他人",
    "交易渠道": "财付通",
    "点进后图标台头": "微信转账",
    "type": "支出",
    "balance": 28586.79,
    "icon": "转账给他人",
    "amount": -2487,
    "date": "2019/07/05 21:25:17",
    "ymd": "2019/07/05",
    "time": "21:26:18",
    "abstract": "财付通-微信转账",
    "title": "微信转账",
    "channel": "财付通",
    "dealType": "网联协议支付"
  },
  {
    "日期": "2019/07/05 21:23:17",
    "时间": "21:24:07",
    "收入": 1000,
    "余额": 31073.79,
    "显示摘要": "许宝丹4075转账",
    "银行交易类型": "客户转账",
    "分类标识": "他人转入",
    "交易渠道": "无",
    "点进后图标台头": "许宝丹",
    "__EMPTY_2": "中国农业银行",
    "__EMPTY_3": "6228***********4075",
    "type": "收入",
    "balance": 31073.79,
    "icon": "他人转入",
    "amount": 1000,
    "date": "2019/07/05 21:23:17",
    "ymd": "2019/07/05",
    "time": "21:24:07",
    "abstract": "许宝丹4075转账",
    "title": "许宝丹",
    "channel": "无",
    "dealType": "客户转账"
  },
  {
    "日期": "2019/07/05 21:20:16",
    "时间": "21:21:37",
    "收入": 28968,
    "余额": 30073.79,
    "显示摘要": "许宝丹4075转账",
    "银行交易类型": "客户转账",
    "分类标识": "他人转入",
    "交易渠道": "无",
    "点进后图标台头": "许宝丹",
    "__EMPTY_2": "中国农业银行",
    "__EMPTY_3": "6228***********4075",
    "type": "收入",
    "balance": 30073.79,
    "icon": "他人转入",
    "amount": 28968,
    "date": "2019/07/05 21:20:16",
    "ymd": "2019/07/05",
    "time": "21:21:37",
    "abstract": "许宝丹4075转账",
    "title": "许宝丹",
    "channel": "无",
    "dealType": "客户转账"
  },
  {
    "income": 39968,
    "expend": 52857.44,
    "hz": "20197"
  },
  {
    "__EMPTY": "2019-05-31T15:59:17.000Z",
    "日期": "2019/06/29 20:47:17",
    "时间": "20:48:23",
    "支出": 1000,
    "余额": 265.49,
    "显示摘要": "财付通-首汽约车",
    "银行交易类型": "网联协议支付",
    "分类标识": "出行",
    "交易渠道": "财付通",
    "点进后图标台头": "首汽约车",
    "type": "支出",
    "balance": 265.49,
    "icon": "出行",
    "amount": -1000,
    "date": "2019/06/29 20:47:17",
    "ymd": "2019/06/29",
    "time": "20:48:23",
    "abstract": "财付通-首汽约车",
    "title": "首汽约车",
    "channel": "财付通",
    "dealType": "网联协议支付"
  },
  {
    "日期": "2019/06/29 20:46:16",
    "时间": "20:47:22",
    "收入": 1000,
    "余额": 1265.49,
    "显示摘要": "葛晓君8562转账",
    "银行交易类型": "行内转入",
    "分类标识": "转账给自己",
    "__EMPTY_1": "不计入",
    "点进后图标台头": "葛晓君",
    "type": "收入",
    "balance": 1265.49,
    "icon": "转账给自己",
    "amount": 1000,
    "date": "2019/06/29 20:46:16",
    "ymd": "2019/06/29",
    "time": "20:47:22",
    "abstract": "葛晓君8562转账",
    "title": "葛晓君",
    "dealType": "行内转入"
  },
  {
    "日期": "2019/06/26 18:53:16",
    "时间": "18:54:55",
    "支出": 97,
    "余额": 265.49,
    "显示摘要": "财付通-微信转账",
    "银行交易类型": "网联协议支付",
    "分类标识": "转账给他人",
    "交易渠道": "财付通",
    "点进后图标台头": "微信转账",
    "type": "支出",
    "balance": 265.49,
    "icon": "转账给他人",
    "amount": -97,
    "date": "2019/06/26 18:53:16",
    "ymd": "2019/06/26",
    "time": "18:54:55",
    "abstract": "财付通-微信转账",
    "title": "微信转账",
    "channel": "财付通",
    "dealType": "网联协议支付"
  },
  {
    "日期": "2019/06/24 15:36:16",
    "时间": "15:37:13",
    "支出": 5000,
    "余额": 362.49,
    "显示摘要": "财付通-微信转账",
    "银行交易类型": "网联协议支付",
    "分类标识": "转账给他人",
    "交易渠道": "财付通",
    "点进后图标台头": "微信转账",
    "type": "支出",
    "balance": 362.49,
    "icon": "转账给他人",
    "amount": -5000,
    "date": "2019/06/24 15:36:16",
    "ymd": "2019/06/24",
    "time": "15:37:13",
    "abstract": "财付通-微信转账",
    "title": "微信转账",
    "channel": "财付通",
    "dealType": "网联协议支付"
  },
  {
    "日期": "2019/06/24 15:35:17",
    "时间": "15:36:01",
    "收入": 5000,
    "余额": 5362.49,
    "显示摘要": "葛晓君8562转账",
    "银行交易类型": "行内转入",
    "分类标识": "转账给自己",
    "__EMPTY_1": "不计入",
    "点进后图标台头": "葛晓君",
    "type": "收入",
    "balance": 5362.49,
    "icon": "转账给自己",
    "amount": 5000,
    "date": "2019/06/24 15:35:17",
    "ymd": "2019/06/24",
    "time": "15:36:01",
    "abstract": "葛晓君8562转账",
    "title": "葛晓君",
    "dealType": "行内转入"
  },
  {
    "日期": "2019/06/21 20:30:16",
    "时间": "20:31:21",
    "支出": 3,
    "余额": 362.49,
    "显示摘要": "支付宝-湖南快乐阳光互动...",
    "银行交易类型": "网联协议支付",
    "分类标识": "休闲娱乐",
    "交易渠道": "支付宝",
    "点进后图标台头": "湖南快乐阳光互动娱乐传媒有限公司",
    "type": "支出",
    "balance": 362.49,
    "icon": "休闲娱乐",
    "amount": -3,
    "date": "2019/06/21 20:30:16",
    "ymd": "2019/06/21",
    "time": "20:31:21",
    "abstract": "支付宝-湖南快乐阳光互动...",
    "title": "湖南快乐阳光互动娱乐传媒有限公司",
    "channel": "支付宝",
    "dealType": "网联协议支付"
  },
  {
    "日期": "2019/06/21 18:03:17",
    "时间": "18:04:09",
    "支出": 200,
    "余额": 365.49,
    "显示摘要": "财付通-微信转账",
    "银行交易类型": "网联协议支付",
    "分类标识": "转账给他人",
    "交易渠道": "财付通",
    "点进后图标台头": "微信转账",
    "type": "支出",
    "balance": 365.49,
    "icon": "转账给他人",
    "amount": -200,
    "date": "2019/06/21 18:03:17",
    "ymd": "2019/06/21",
    "time": "18:04:09",
    "abstract": "财付通-微信转账",
    "title": "微信转账",
    "channel": "财付通",
    "dealType": "网联协议支付"
  },
  {
    "日期": "2019/06/21 02:34:17",
    "时间": "02:35:31",
    "收入": 0.42,
    "余额": 565.49,
    "显示摘要": "结息：0.42扣税：0.00",
    "银行交易类型": "账户结息",
    "分类标识": "投资收益",
    "点进后图标台头": "结息：0.42扣税：0.00",
    "type": "收入",
    "balance": 565.49,
    "icon": "投资收益",
    "amount": 0.42,
    "date": "2019/06/21 02:34:17",
    "ymd": "2019/06/21",
    "time": "02:35:31",
    "abstract": "结息：0.42扣税：0.00",
    "title": "结息：0.42扣税：0.00",
    "dealType": "账户结息"
  },
  {
    "日期": "2019/06/16 16:08:17",
    "时间": "16:09:33",
    "支出": 1000,
    "余额": 565.07,
    "显示摘要": "财付通-首汽约车",
    "银行交易类型": "网联协议支付",
    "分类标识": "出行",
    "交易渠道": "财付通",
    "点进后图标台头": "首汽约车",
    "type": "支出",
    "balance": 565.07,
    "icon": "出行",
    "amount": -1000,
    "date": "2019/06/16 16:08:17",
    "ymd": "2019/06/16",
    "time": "16:09:33",
    "abstract": "财付通-首汽约车",
    "title": "首汽约车",
    "channel": "财付通",
    "dealType": "网联协议支付"
  },
  {
    "日期": "2019/06/16 16:07:16",
    "时间": "16:08:44",
    "收入": 1000,
    "余额": 1565.07,
    "显示摘要": "葛晓君8562转账",
    "银行交易类型": "行内转入",
    "分类标识": "转账给自己",
    "__EMPTY_1": "不计入",
    "点进后图标台头": "葛晓君",
    "type": "收入",
    "balance": 1565.07,
    "icon": "转账给自己",
    "amount": 1000,
    "date": "2019/06/16 16:07:16",
    "ymd": "2019/06/16",
    "time": "16:08:44",
    "abstract": "葛晓君8562转账",
    "title": "葛晓君",
    "dealType": "行内转入"
  },
  {
    "日期": "2019/06/15 17:59:17",
    "时间": "18:00:23",
    "支出": 22.5,
    "余额": 565.07,
    "显示摘要": "财付通-腾讯财付通-微信转账",
    "银行交易类型": "银联快捷支付",
    "分类标识": "转账给他人",
    "交易渠道": "财付通",
    "点进后图标台头": "微信转账",
    "type": "支出",
    "balance": 565.07,
    "icon": "转账给他人",
    "amount": -22.5,
    "date": "2019/06/15 17:59:17",
    "ymd": "2019/06/15",
    "time": "18:00:23",
    "abstract": "财付通-腾讯财付通-微信转账",
    "title": "微信转账",
    "channel": "财付通",
    "dealType": "银联快捷支付"
  },
  {
    "日期": "2019/06/14 22:49:17",
    "时间": "22:50:00",
    "支出": 84.34,
    "余额": 587.57,
    "显示摘要": "财付通-首汽约车",
    "银行交易类型": "网联协议支付",
    "分类标识": "出行",
    "交易渠道": "财付通",
    "点进后图标台头": "首汽约车",
    "type": "支出",
    "balance": 587.57,
    "icon": "出行",
    "amount": -84.34,
    "date": "2019/06/14 22:49:17",
    "ymd": "2019/06/14",
    "time": "22:50:00",
    "abstract": "财付通-首汽约车",
    "title": "首汽约车",
    "channel": "财付通",
    "dealType": "网联协议支付"
  },
  {
    "日期": "2019/06/14 14:49:17",
    "时间": "14:50:45",
    "支出": 400,
    "余额": 671.91,
    "显示摘要": "财付通-微信转账",
    "银行交易类型": "网联协议支付",
    "分类标识": "转账给他人",
    "交易渠道": "财付通",
    "点进后图标台头": "微信转账",
    "type": "支出",
    "balance": 671.91,
    "icon": "转账给他人",
    "amount": -400,
    "date": "2019/06/14 14:49:17",
    "ymd": "2019/06/14",
    "time": "14:50:45",
    "abstract": "财付通-微信转账",
    "title": "微信转账",
    "channel": "财付通",
    "dealType": "网联协议支付"
  },
  {
    "日期": "2019/06/12 23:51:16",
    "时间": "23:52:29",
    "支出": 35.9,
    "余额": 1071.91,
    "显示摘要": "财付通-京东商城平台商户",
    "银行交易类型": "网联协议支付",
    "分类标识": "购物",
    "交易渠道": "财付通",
    "点进后图标台头": "京东商城平台商户",
    "type": "支出",
    "balance": 1071.91,
    "icon": "购物",
    "amount": -35.9,
    "date": "2019/06/12 23:51:16",
    "ymd": "2019/06/12",
    "time": "23:52:29",
    "abstract": "财付通-京东商城平台商户",
    "title": "京东商城平台商户",
    "channel": "财付通",
    "dealType": "网联协议支付"
  },
  {
    "日期": "2019/06/12 23:50:17",
    "时间": "23:51:08",
    "支出": 39.8,
    "余额": 1107.81,
    "显示摘要": "财付通-京东商城平台商户",
    "银行交易类型": "网联协议支付",
    "分类标识": "购物",
    "交易渠道": "财付通",
    "点进后图标台头": "京东商城平台商户",
    "type": "支出",
    "balance": 1107.81,
    "icon": "购物",
    "amount": -39.8,
    "date": "2019/06/12 23:50:17",
    "ymd": "2019/06/12",
    "time": "23:51:08",
    "abstract": "财付通-京东商城平台商户",
    "title": "京东商城平台商户",
    "channel": "财付通",
    "dealType": "网联协议支付"
  },
  {
    "日期": "2019/06/12 18:15:16",
    "时间": "18:16:23",
    "支出": 26.49,
    "余额": 1147.61,
    "显示摘要": "财付通-首汽约车",
    "银行交易类型": "网联协议支付",
    "分类标识": "出行",
    "交易渠道": "财付通",
    "点进后图标台头": "首汽约车",
    "type": "支出",
    "balance": 1147.61,
    "icon": "出行",
    "amount": -26.49,
    "date": "2019/06/12 18:15:16",
    "ymd": "2019/06/12",
    "time": "18:16:23",
    "abstract": "财付通-首汽约车",
    "title": "首汽约车",
    "channel": "财付通",
    "dealType": "网联协议支付"
  },
  {
    "income": 0.42,
    "expend": 7909.03,
    "hz": "20196"
  },
  {
    "__EMPTY": "2019-04-30T15:59:17.000Z",
    "日期": "2019/05/31 20:30:16",
    "时间": "20:31:32",
    "收入": 1329,
    "余额": 1952.7,
    "显示摘要": "支付宝-Sky Credit（HongKo...",
    "银行交易类型": "网联退款",
    "分类标识": "退款",
    "点进后图标台头": "支付宝-Sky Credit(HongKong)",
    "type": "收入",
    "balance": 1952.7,
    "icon": "退款",
    "amount": 1329,
    "date": "2019/05/31 20:30:16",
    "ymd": "2019/05/31",
    "time": "20:31:32",
    "abstract": "支付宝-Sky Credit（HongKo...",
    "title": "支付宝-Sky Credit(HongKong)",
    "dealType": "网联退款"
  },
  {
    "日期": "2019/05/31 14:45:17",
    "时间": "14:46:57",
    "支出": 3712.63,
    "余额": 623.7,
    "显示摘要": "财付通-AGODA安可达",
    "银行交易类型": "网联协议支付",
    "分类标识": "酒店",
    "交易渠道": "财付通",
    "点进后图标台头": "AGODA安可达",
    "type": "支出",
    "balance": 623.7,
    "icon": "酒店",
    "amount": -3712.63,
    "date": "2019/05/31 14:45:17",
    "ymd": "2019/05/31",
    "time": "14:46:57",
    "abstract": "财付通-AGODA安可达",
    "title": "AGODA安可达",
    "channel": "财付通",
    "dealType": "网联协议支付"
  },
  {
    "日期": "2019/05/31 14:45:17",
    "时间": "14:46:17",
    "收入": 4000,
    "余额": 4336.33,
    "显示摘要": "葛晓君8562转账",
    "银行交易类型": "行内转入",
    "分类标识": "转账给自己",
    "__EMPTY_1": "不计入",
    "点进后图标台头": "葛晓君",
    "type": "收入",
    "balance": 4336.33,
    "icon": "转账给自己",
    "amount": 4000,
    "date": "2019/05/31 14:45:17",
    "ymd": "2019/05/31",
    "time": "14:46:17",
    "abstract": "葛晓君8562转账",
    "title": "葛晓君",
    "dealType": "行内转入"
  },
  {
    "日期": "2019/05/31 11:19:16",
    "时间": "11:20:24",
    "支出": 1,
    "余额": 336.33,
    "显示摘要": "财付通-腾讯财付通-格格小区",
    "银行交易类型": "银联快捷支付",
    "分类标识": "其他支出",
    "点进后图标台头": "财付通-腾讯财付通-格格小区",
    "type": "支出",
    "balance": 336.33,
    "icon": "其他支出",
    "amount": -1,
    "date": "2019/05/31 11:19:16",
    "ymd": "2019/05/31",
    "time": "11:20:24",
    "abstract": "财付通-腾讯财付通-格格小区",
    "title": "财付通-腾讯财付通-格格小区",
    "dealType": "银联快捷支付"
  },
  {
    "日期": "2019/05/30 22:13:17",
    "时间": "22:14:46",
    "支出": 5060,
    "余额": 337.33,
    "显示摘要": "财付通-北京大学第一医院",
    "银行交易类型": "网联协议支付",
    "分类标识": "医疗保健",
    "交易渠道": "财付通",
    "点进后图标台头": "北京大学第一医院",
    "type": "支出",
    "balance": 337.33,
    "icon": "医疗保健",
    "amount": -5060,
    "date": "2019/05/30 22:13:17",
    "ymd": "2019/05/30",
    "time": "22:14:46",
    "abstract": "财付通-北京大学第一医院",
    "title": "北京大学第一医院",
    "channel": "财付通",
    "dealType": "网联协议支付"
  },
  {
    "__EMPTY": "重点条目",
    "日期": "2019/05/27 16:26:17",
    "时间": "16:27:00",
    "支出": 34000,
    "余额": 5397.33,
    "显示摘要": "北京市雍雅餐饮有限公司",
    "银行交易类型": "银联POS消费",
    "分类标识": "餐饮",
    "交易渠道": "无",
    "点进后图标台头": "北京市雍雅餐饮有限公司",
    "type": "支出",
    "balance": 5397.33,
    "icon": "餐饮",
    "amount": -34000,
    "date": "2019/05/27 16:26:17",
    "ymd": "2019/05/27",
    "time": "16:27:00",
    "abstract": "北京市雍雅餐饮有限公司",
    "title": "北京市雍雅餐饮有限公司",
    "channel": "无",
    "dealType": "银联POS消费"
  },
  {
    "日期": "2019/05/26 19:39:16",
    "时间": "19:40:06",
    "支出": 44.9,
    "余额": 39397.33,
    "显示摘要": "财付通-京东商城平台商户",
    "银行交易类型": "网联协议支付",
    "分类标识": "购物",
    "交易渠道": "财付通",
    "点进后图标台头": "京东商城平台商户",
    "type": "支出",
    "balance": 39397.33,
    "icon": "购物",
    "amount": -44.9,
    "date": "2019/05/26 19:39:16",
    "ymd": "2019/05/26",
    "time": "19:40:06",
    "abstract": "财付通-京东商城平台商户",
    "title": "京东商城平台商户",
    "channel": "财付通",
    "dealType": "网联协议支付"
  },
  {
    "日期": "2019/05/26 19:37:17",
    "时间": "19:38:41",
    "支出": 161.47,
    "余额": 39442.23,
    "显示摘要": "财付通-JD",
    "银行交易类型": "网联协议支付",
    "分类标识": "购物",
    "交易渠道": "财付通",
    "点进后图标台头": "JD",
    "type": "支出",
    "balance": 39442.23,
    "icon": "购物",
    "amount": -161.47,
    "date": "2019/05/26 19:37:17",
    "ymd": "2019/05/26",
    "time": "19:38:41",
    "abstract": "财付通-JD",
    "title": "JD",
    "channel": "财付通",
    "dealType": "网联协议支付"
  },
  {
    "日期": "2019/05/26 17:13:17",
    "时间": "17:14:25",
    "支出": 1329,
    "余额": 39603.7,
    "显示摘要": "支付宝-Sky Credit（HongKo...",
    "银行交易类型": "网联协议支付",
    "分类标识": "其他支出",
    "交易渠道": "支付宝",
    "点进后图标台头": "Sky Credit(HongKong)Limited",
    "type": "支出",
    "balance": 39603.7,
    "icon": "其他支出",
    "amount": -1329,
    "date": "2019/05/26 17:13:17",
    "ymd": "2019/05/26",
    "time": "17:14:25",
    "abstract": "支付宝-Sky Credit（HongKo...",
    "title": "Sky Credit(HongKong)Limited",
    "channel": "支付宝",
    "dealType": "网联协议支付"
  },
  {
    "日期": "2019/05/26 11:12:16",
    "时间": "11:13:24",
    "支出": 1601,
    "余额": 40932.7,
    "显示摘要": "银联消费北京大学第一医院",
    "银行交易类型": "银联POS消费",
    "分类标识": "医疗保健",
    "交易渠道": "无",
    "点进后图标台头": "北京大学第一医院",
    "type": "支出",
    "balance": 40932.7,
    "icon": "医疗保健",
    "amount": -1601,
    "date": "2019/05/26 11:12:16",
    "ymd": "2019/05/26",
    "time": "11:13:24",
    "abstract": "银联消费北京大学第一医院",
    "title": "北京大学第一医院",
    "channel": "无",
    "dealType": "银联POS消费"
  },
  {
    "日期": "2019/05/25 13:36:16",
    "时间": "13:37:53",
    "支出": 1000,
    "余额": 42533.7,
    "显示摘要": "财付通-首汽约车",
    "银行交易类型": "网联协议支付",
    "分类标识": "出行",
    "交易渠道": "财付通",
    "点进后图标台头": "首汽约车",
    "type": "支出",
    "balance": 42533.7,
    "icon": "出行",
    "amount": -1000,
    "date": "2019/05/25 13:36:16",
    "ymd": "2019/05/25",
    "time": "13:37:53",
    "abstract": "财付通-首汽约车",
    "title": "首汽约车",
    "channel": "财付通",
    "dealType": "网联协议支付"
  },
  {
    "日期": "2019/05/25 08:18:17",
    "时间": "08:19:39",
    "支出": 400,
    "余额": 43533.7,
    "显示摘要": "银联消费中国石油",
    "银行交易类型": "银联POS消费",
    "分类标识": "私家车",
    "交易渠道": "无",
    "点进后图标台头": "中国石油",
    "type": "支出",
    "balance": 43533.7,
    "icon": "私家车",
    "amount": -400,
    "date": "2019/05/25 08:18:17",
    "ymd": "2019/05/25",
    "time": "08:19:39",
    "abstract": "银联消费中国石油",
    "title": "中国石油",
    "channel": "无",
    "dealType": "银联POS消费"
  },
  {
    "日期": "2019/05/24 20:21:16",
    "时间": "20:22:24",
    "支出": 240,
    "余额": 43933.7,
    "显示摘要": "财付通-苏州市钱棉丝绸",
    "银行交易类型": "网联协议支付",
    "分类标识": "其他支出",
    "交易渠道": "财付通",
    "点进后图标台头": "苏州市钱棉丝绸",
    "type": "支出",
    "balance": 43933.7,
    "icon": "其他支出",
    "amount": -240,
    "date": "2019/05/24 20:21:16",
    "ymd": "2019/05/24",
    "time": "20:22:24",
    "abstract": "财付通-苏州市钱棉丝绸",
    "title": "苏州市钱棉丝绸",
    "channel": "财付通",
    "dealType": "网联协议支付"
  },
  {
    "日期": "2019/05/22 09:56:16",
    "时间": "09:57:16",
    "支出": 46,
    "余额": 44173.7,
    "显示摘要": "财付通-闪送",
    "银行交易类型": "网联协议支付",
    "分类标识": "其他支出",
    "交易渠道": "财付通",
    "点进后图标台头": "闪送",
    "type": "支出",
    "balance": 44173.7,
    "icon": "其他支出",
    "amount": -46,
    "date": "2019/05/22 09:56:16",
    "ymd": "2019/05/22",
    "time": "09:57:16",
    "abstract": "财付通-闪送",
    "title": "闪送",
    "channel": "财付通",
    "dealType": "网联协议支付"
  },
  {
    "日期": "2019/05/21 17:38:17",
    "时间": "17:39:26",
    "支出": 883.5,
    "余额": 44219.7,
    "显示摘要": "财付通-中国铁路总公司资...",
    "银行交易类型": "网联协议支付",
    "分类标识": "出行",
    "交易渠道": "财付通",
    "点进后图标台头": "中国铁路总公司资金清",
    "type": "支出",
    "balance": 44219.7,
    "icon": "出行",
    "amount": -883.5,
    "date": "2019/05/21 17:38:17",
    "ymd": "2019/05/21",
    "time": "17:39:26",
    "abstract": "财付通-中国铁路总公司资...",
    "title": "中国铁路总公司资金清",
    "channel": "财付通",
    "dealType": "网联协议支付"
  },
  {
    "日期": "2019/05/21 14:26:16",
    "时间": "14:27:35",
    "支出": 500,
    "余额": 45103.2,
    "显示摘要": "银联ATM取款中国工商银行",
    "银行交易类型": "银联ATM取款",
    "分类标识": "现金取出",
    "点进后图标台头": "银联ATM取款中国工商银行",
    "type": "支出",
    "balance": 45103.2,
    "icon": "现金取出",
    "amount": -500,
    "date": "2019/05/21 14:26:16",
    "ymd": "2019/05/21",
    "time": "14:27:35",
    "abstract": "银联ATM取款中国工商银行",
    "title": "银联ATM取款中国工商银行",
    "dealType": "银联ATM取款"
  },
  {
    "日期": "2019/05/11 20:57:16",
    "时间": "20:58:56",
    "支出": 1000,
    "余额": 45603.2,
    "显示摘要": "财付通-首汽约车",
    "银行交易类型": "网联协议支付",
    "分类标识": "出行",
    "交易渠道": "财付通",
    "点进后图标台头": "首汽约车",
    "type": "支出",
    "balance": 45603.2,
    "icon": "出行",
    "amount": -1000,
    "date": "2019/05/11 20:57:16",
    "ymd": "2019/05/11",
    "time": "20:58:56",
    "abstract": "财付通-首汽约车",
    "title": "首汽约车",
    "channel": "财付通",
    "dealType": "网联协议支付"
  },
  {
    "日期": "2019/05/11 20:54:17",
    "时间": "20:55:24",
    "支出": 246.6,
    "余额": 46603.2,
    "显示摘要": "银联消费北京家爱福美超...",
    "银行交易类型": "银联POS消费",
    "分类标识": "超市便利",
    "交易渠道": "无",
    "点进后图标台头": "北京家爱福美超市",
    "type": "支出",
    "balance": 46603.2,
    "icon": "超市便利",
    "amount": -246.6,
    "date": "2019/05/11 20:54:17",
    "ymd": "2019/05/11",
    "time": "20:55:24",
    "abstract": "银联消费北京家爱福美超...",
    "title": "北京家爱福美超市",
    "channel": "无",
    "dealType": "银联POS消费"
  },
  {
    "日期": "2019/05/10 21:09:16",
    "时间": "21:10:14",
    "支出": 787.8,
    "余额": 46849.8,
    "显示摘要": "财付通-京东商城平台商户",
    "银行交易类型": "网联协议支付",
    "分类标识": "购物",
    "交易渠道": "财付通",
    "点进后图标台头": "京东商城平台商户",
    "type": "支出",
    "balance": 46849.8,
    "icon": "购物",
    "amount": -787.8,
    "date": "2019/05/10 21:09:16",
    "ymd": "2019/05/10",
    "time": "21:10:14",
    "abstract": "财付通-京东商城平台商户",
    "title": "京东商城平台商户",
    "channel": "财付通",
    "dealType": "网联协议支付"
  },
  {
    "日期": "2019/05/10 18:36:16",
    "时间": "18:37:00",
    "支出": 1280,
    "余额": 47637.6,
    "显示摘要": "银联消费玛俪琳商贸...",
    "银行交易类型": "银联POS消费",
    "分类标识": "其他支出",
    "交易渠道": "无",
    "点进后图标台头": "玛俪琳商贸有限公司朝阳分*",
    "type": "支出",
    "balance": 47637.6,
    "icon": "其他支出",
    "amount": -1280,
    "date": "2019/05/10 18:36:16",
    "ymd": "2019/05/10",
    "time": "18:37:00",
    "abstract": "银联消费玛俪琳商贸...",
    "title": "玛俪琳商贸有限公司朝阳分*",
    "channel": "无",
    "dealType": "银联POS消费"
  },
  {
    "日期": "2019/05/05 21:40:16",
    "时间": "21:41:00",
    "支出": 1538,
    "余额": 39821.11,
    "显示摘要": "财付通-微信转账",
    "type": "支出",
    "balance": 39821.11,
    "amount": -1538,
    "date": "2019/05/05 21:40:16",
    "ymd": "2019/05/05",
    "time": "21:41:00",
    "abstract": "财付通-微信转账"
  },
  {
    "日期": "2019/05/05 12:31:16",
    "时间": "12:32:35",
    "收入": 40858,
    "余额": 41359.11,
    "显示摘要": "史新华0655跨行转账",
    "type": "收入",
    "balance": 41359.11,
    "amount": 40858,
    "date": "2019/05/05 12:31:16",
    "ymd": "2019/05/05",
    "time": "12:32:35",
    "abstract": "史新华0655跨行转账"
  },
  {
    "income": 42187,
    "expend": 53831.9,
    "hz": "20195"
  },
  {
    "__EMPTY": "2019-03-31T15:59:17.000Z",
    "日期": "2019/04/30 21:46:17",
    "时间": "21:47:36",
    "支出": 88,
    "余额": 1173.49,
    "显示摘要": "财付通-视云影院",
    "银行交易类型": "网联协议支付",
    "分类标识": "休闲娱乐",
    "交易渠道": "财付通",
    "点进后图标台头": "视云影院",
    "type": "支出",
    "balance": 1173.49,
    "icon": "休闲娱乐",
    "amount": -88,
    "date": "2019/04/30 21:46:17",
    "ymd": "2019/04/30",
    "time": "21:47:36",
    "abstract": "财付通-视云影院",
    "title": "视云影院",
    "channel": "财付通",
    "dealType": "网联协议支付"
  },
  {
    "日期": "2019/04/30 20:58:17",
    "时间": "20:59:04",
    "支出": 284.9,
    "余额": 1261.49,
    "显示摘要": "财付通-汤山百年绿源",
    "银行交易类型": "网联协议支付",
    "分类标识": "其他支出",
    "交易渠道": "财付通",
    "点进后图标台头": "汤山百年绿源",
    "type": "支出",
    "balance": 1261.49,
    "icon": "其他支出",
    "amount": -284.9,
    "date": "2019/04/30 20:58:17",
    "ymd": "2019/04/30",
    "time": "20:59:04",
    "abstract": "财付通-汤山百年绿源",
    "title": "汤山百年绿源",
    "channel": "财付通",
    "dealType": "网联协议支付"
  },
  {
    "日期": "2019/04/30 18:00:16",
    "时间": "18:01:41",
    "支出": 53,
    "余额": 1546.39,
    "显示摘要": "财付通-腾讯财付通-微信转账",
    "银行交易类型": "银联快捷支付",
    "分类标识": "转账给他人",
    "交易渠道": "财付通",
    "点进后图标台头": "微信转账",
    "type": "支出",
    "balance": 1546.39,
    "icon": "转账给他人",
    "amount": -53,
    "date": "2019/04/30 18:00:16",
    "ymd": "2019/04/30",
    "time": "18:01:41",
    "abstract": "财付通-腾讯财付通-微信转账",
    "title": "微信转账",
    "channel": "财付通",
    "dealType": "银联快捷支付"
  },
  {
    "日期": "2019/04/29 16:16:16",
    "时间": "16:17:05",
    "支出": 890,
    "余额": 1599.39,
    "显示摘要": "财付通-昭德（杭州）酒",
    "type": "支出",
    "balance": 1599.39,
    "amount": -890,
    "date": "2019/04/29 16:16:16",
    "ymd": "2019/04/29",
    "time": "16:17:05",
    "abstract": "财付通-昭德（杭州）酒"
  },
  {
    "日期": "2019/04/29 16:08:17",
    "时间": "16:09:47",
    "收入": 2000,
    "余额": 2489.39,
    "显示摘要": "葛晓君8562转账",
    "银行交易类型": "行内转入",
    "分类标识": "转账给自己",
    "__EMPTY_1": "不计入",
    "点进后图标台头": "葛晓君",
    "type": "收入",
    "balance": 2489.39,
    "icon": "转账给自己",
    "amount": 2000,
    "date": "2019/04/29 16:08:17",
    "ymd": "2019/04/29",
    "time": "16:09:47",
    "abstract": "葛晓君8562转账",
    "title": "葛晓君",
    "dealType": "行内转入"
  },
  {
    "日期": "2019/04/26 23:00:17",
    "时间": "23:01:03",
    "支出": 70.5,
    "余额": 489.39,
    "显示摘要": "财付通-e代驾",
    "type": "支出",
    "balance": 489.39,
    "amount": -70.5,
    "date": "2019/04/26 23:00:17",
    "ymd": "2019/04/26",
    "time": "23:01:03",
    "abstract": "财付通-e代驾"
  },
  {
    "日期": "2019/04/25 19:36:16",
    "时间": "19:37:48",
    "收入": 59,
    "余额": 559.89,
    "显示摘要": "退 支付宝-石狮市咏婷服装...",
    "type": "收入",
    "balance": 559.89,
    "amount": 59,
    "date": "2019/04/25 19:36:16",
    "ymd": "2019/04/25",
    "time": "19:37:48",
    "abstract": "退 支付宝-石狮市咏婷服装..."
  },
  {
    "日期": "2019/04/25 18:14:17",
    "时间": "18:15:32",
    "支出": 7.5,
    "余额": 500.89,
    "显示摘要": "财付通-腾讯财付通-微信转账",
    "type": "支出",
    "balance": 500.89,
    "amount": -7.5,
    "date": "2019/04/25 18:14:17",
    "ymd": "2019/04/25",
    "time": "18:15:32",
    "abstract": "财付通-腾讯财付通-微信转账"
  },
  {
    "日期": "2019/04/25 18:12:17",
    "时间": "18:13:22",
    "支出": 21.25,
    "余额": 508.39,
    "显示摘要": "财付通-腾讯财付通-微信转账",
    "type": "支出",
    "balance": 508.39,
    "amount": -21.25,
    "date": "2019/04/25 18:12:17",
    "ymd": "2019/04/25",
    "time": "18:13:22",
    "abstract": "财付通-腾讯财付通-微信转账"
  },
  {
    "日期": "2019/04/25 18:11:16",
    "时间": "18:12:35",
    "支出": 43.75,
    "余额": 529.64,
    "显示摘要": "财付通-北京市西城区城...",
    "type": "支出",
    "balance": 529.64,
    "amount": -43.75,
    "date": "2019/04/25 18:11:16",
    "ymd": "2019/04/25",
    "time": "18:12:35",
    "abstract": "财付通-北京市西城区城..."
  },
  {
    "日期": "2019/04/25 18:10:17",
    "时间": "18:11:12",
    "支出": 7.5,
    "余额": 573.39,
    "显示摘要": "财付通-北京市西城区城...",
    "type": "支出",
    "balance": 573.39,
    "amount": -7.5,
    "date": "2019/04/25 18:10:17",
    "ymd": "2019/04/25",
    "time": "18:11:12",
    "abstract": "财付通-北京市西城区城..."
  },
  {
    "日期": "2019/04/25 18:08:16",
    "时间": "18:09:35",
    "支出": 13.75,
    "余额": 580.89,
    "显示摘要": "财付通-北京市西城区城...",
    "type": "支出",
    "balance": 580.89,
    "amount": -13.75,
    "date": "2019/04/25 18:08:16",
    "ymd": "2019/04/25",
    "time": "18:09:35",
    "abstract": "财付通-北京市西城区城..."
  },
  {
    "日期": "2019/04/25 18:07:17",
    "时间": "18:08:12",
    "支出": 32.5,
    "余额": 594.64,
    "显示摘要": "财付通-北京市西城区城...",
    "type": "支出",
    "balance": 594.64,
    "amount": -32.5,
    "date": "2019/04/25 18:07:17",
    "ymd": "2019/04/25",
    "time": "18:08:12",
    "abstract": "财付通-北京市西城区城..."
  },
  {
    "日期": "2019/04/25 18:05:17",
    "时间": "18:06:04",
    "支出": 85,
    "余额": 627.14,
    "显示摘要": "财付通-北京市西城区城...",
    "type": "支出",
    "balance": 627.14,
    "amount": -85,
    "date": "2019/04/25 18:05:17",
    "ymd": "2019/04/25",
    "time": "18:06:04",
    "abstract": "财付通-北京市西城区城..."
  },
  {
    "日期": "2019/04/24 11:36:17",
    "时间": "11:37:48",
    "支出": 15,
    "余额": 712.14,
    "显示摘要": "支付宝-浙江菜鸟供应链...",
    "type": "支出",
    "balance": 712.14,
    "amount": -15,
    "date": "2019/04/24 11:36:17",
    "ymd": "2019/04/24",
    "time": "11:37:48",
    "abstract": "支付宝-浙江菜鸟供应链..."
  },
  {
    "日期": "2019/04/23 09:38:16",
    "时间": "19:39:04",
    "支出": 88.7,
    "余额": 727.14,
    "显示摘要": "财付通-京东商城平台商户",
    "type": "支出",
    "balance": 727.14,
    "amount": -88.7,
    "date": "2019/04/23 09:38:16",
    "ymd": "2019/04/23",
    "time": "19:39:04",
    "abstract": "财付通-京东商城平台商户"
  },
  {
    "日期": "2019/04/23 19:35:17",
    "时间": "19:36:57",
    "支出": 128,
    "余额": 815.84,
    "显示摘要": "财付通-汤山百年绿源",
    "type": "支出",
    "balance": 815.84,
    "amount": -128,
    "date": "2019/04/23 19:35:17",
    "ymd": "2019/04/23",
    "time": "19:36:57",
    "abstract": "财付通-汤山百年绿源"
  },
  {
    "日期": "2019/04/10 23:26:16",
    "时间": "23:27:00",
    "收入": 1000,
    "余额": 1000,
    "显示摘要": "葛晓君8562转账",
    "type": "收入",
    "balance": 1000,
    "amount": 1000,
    "date": "2019/04/10 23:26:16",
    "ymd": "2019/04/10",
    "time": "23:27:00",
    "abstract": "葛晓君8562转账"
  },
  {
    "日期": "2019/04/08 17:53:16",
    "时间": "17:54:00",
    "支出": 3240,
    "余额": 467.57,
    "显示摘要": "财付通-微信转账",
    "type": "支出",
    "balance": 467.57,
    "amount": -3240,
    "date": "2019/04/08 17:53:16",
    "ymd": "2019/04/08",
    "time": "17:54:00",
    "abstract": "财付通-微信转账"
  },
  {
    "日期": "2019/04/02 11:46:16",
    "时间": "11:47:26",
    "收入": 3700,
    "余额": 3707.57,
    "显示摘要": "葛晓君8562转账",
    "type": "收入",
    "balance": 3707.57,
    "amount": 3700,
    "date": "2019/04/02 11:46:16",
    "ymd": "2019/04/02",
    "time": "11:47:26",
    "abstract": "葛晓君8562转账"
  },
  {
    "日期": "2019/04/01 13:55:17",
    "时间": "13:56:49",
    "支出": 993.12,
    "余额": 7.57,
    "显示摘要": "财付通-北京大学第一医院",
    "type": "支出",
    "balance": 7.57,
    "amount": -993.12,
    "date": "2019/04/01 13:55:17",
    "ymd": "2019/04/01",
    "time": "13:56:49",
    "abstract": "财付通-北京大学第一医院"
  },
  {
    "日期": "2019/04/01 13:54:16",
    "时间": "13:55:02",
    "收入": 1000,
    "余额": 1000.69,
    "显示摘要": "葛晓君8562转账",
    "type": "收入",
    "balance": 1000.69,
    "amount": 1000,
    "date": "2019/04/01 13:54:16",
    "ymd": "2019/04/01",
    "time": "13:55:02",
    "abstract": "葛晓君8562转账"
  },
  {
    "income": 59,
    "expend": 6062.47,
    "hz": "20194"
  },
  {
    "__EMPTY": "2019-02-28T15:59:17.000Z",
    "日期": "2019/03/21 12:29:16",
    "时间": "12:30:40",
    "收入": 0.69,
    "余额": 0.69,
    "显示摘要": "结息：0.69扣税：0.00",
    "type": "收入",
    "balance": 0.69,
    "amount": 0.69,
    "date": "2019/03/21 12:29:16",
    "ymd": "2019/03/21",
    "time": "12:30:40",
    "abstract": "结息：0.69扣税：0.00"
  },
  {
    "日期": "2019/03/08 17:42:16",
    "时间": "17:43:49",
    "支出": 2323.1,
    "余额": 0,
    "显示摘要": "20190308A0011001...",
    "__EMPTY_1": "不计入",
    "type": "支出",
    "balance": 0,
    "amount": -2323.1,
    "date": "2019/03/08 17:42:16",
    "ymd": "2019/03/08",
    "time": "17:43:49",
    "abstract": "20190308A0011001..."
  },
  {
    "income": 0.69,
    "expend": 0,
    "hz": "20193"
  }
]